{
  "symbol": "MANAUSDT",
  "interval": "1m",
  "fetched_at": "2025-11-13T05:01:04.088745+00:00",
  "candles": [
    {
      "timestamp": 1762972620000,
      "open": 0.2211,
      "high": 0.2212,
      "low": 0.2211,
      "close": 0.2212,
      "volume": 1046.0
    },
    {
      "timestamp": 1762972680000,
      "open": 0.2212,
      "high": 0.2212,
      "low": 0.221,
      "close": 0.221,
      "volume": 10856.0
    },
    {
      "timestamp": 1762972740000,
      "open": 0.2212,
      "high": 0.2214,
      "low": 0.2212,
      "close": 0.2214,
      "volume": 3065.0
    },
    {
      "timestamp": 1762972800000,
      "open": 0.2214,
      "high": 0.2215,
      "low": 0.2213,
      "close": 0.2214,
      "volume": 8813.0
    },
    {
      "timestamp": 1762972860000,
      "open": 0.2212,
      "high": 0.2212,
      "low": 0.2207,
      "close": 0.2208,
      "volume": 39064.0
    },
    {
      "timestamp": 1762972920000,
      "open": 0.2206,
      "high": 0.2207,
      "low": 0.2206,
      "close": 0.2207,
      "volume": 3636.0
    },
    {
      "timestamp": 1762972980000,
      "open": 0.2207,
      "high": 0.2209,
      "low": 0.2207,
      "close": 0.2209,
      "volume": 217.0
    },
    {
      "timestamp": 1762973040000,
      "open": 0.2208,
      "high": 0.2208,
      "low": 0.2208,
      "close": 0.2208,
      "volume": 3210.0
    },
    {
      "timestamp": 1762973100000,
      "open": 0.2207,
      "high": 0.2207,
      "low": 0.2205,
      "close": 0.2205,
      "volume": 818.0
    },
    {
      "timestamp": 1762973160000,
      "open": 0.2205,
      "high": 0.2205,
      "low": 0.2202,
      "close": 0.2203,
      "volume": 2074.0
    },
    {
      "timestamp": 1762973220000,
      "open": 0.2201,
      "high": 0.2203,
      "low": 0.22,
      "close": 0.2203,
      "volume": 463.0
    },
    {
      "timestamp": 1762973280000,
      "open": 0.2202,
      "high": 0.2202,
      "low": 0.2199,
      "close": 0.2199,
      "volume": 1504.0
    },
    {
      "timestamp": 1762973340000,
      "open": 0.2199,
      "high": 0.2199,
      "low": 0.2193,
      "close": 0.2193,
      "volume": 48918.0
    },
    {
      "timestamp": 1762973400000,
      "open": 0.2193,
      "high": 0.2193,
      "low": 0.2191,
      "close": 0.2193,
      "volume": 5107.0
    },
    {
      "timestamp": 1762973460000,
      "open": 0.2193,
      "high": 0.2195,
      "low": 0.2193,
      "close": 0.2195,
      "volume": 3296.0
    },
    {
      "timestamp": 1762973520000,
      "open": 0.2195,
      "high": 0.2196,
      "low": 0.2195,
      "close": 0.2196,
      "volume": 7514.0
    },
    {
      "timestamp": 1762973580000,
      "open": 0.2194,
      "high": 0.2194,
      "low": 0.2193,
      "close": 0.2193,
      "volume": 6634.0
    },
    {
      "timestamp": 1762973640000,
      "open": 0.2194,
      "high": 0.2194,
      "low": 0.2194,
      "close": 0.2194,
      "volume": 46.0
    },
    {
      "timestamp": 1762973700000,
      "open": 0.2195,
      "high": 0.2196,
      "low": 0.2194,
      "close": 0.2196,
      "volume": 1341.0
    },
    {
      "timestamp": 1762973760000,
      "open": 0.2196,
      "high": 0.2196,
      "low": 0.2196,
      "close": 0.2196,
      "volume": 0.0
    },
    {
      "timestamp": 1762973820000,
      "open": 0.2195,
      "high": 0.2196,
      "low": 0.2195,
      "close": 0.2196,
      "volume": 859.0
    },
    {
      "timestamp": 1762973880000,
      "open": 0.2195,
      "high": 0.2195,
      "low": 0.2193,
      "close": 0.2193,
      "volume": 1137.0
    },
    {
      "timestamp": 1762973940000,
      "open": 0.2193,
      "high": 0.2193,
      "low": 0.2191,
      "close": 0.2191,
      "volume": 3772.0
    },
    {
      "timestamp": 1762974000000,
      "open": 0.219,
      "high": 0.219,
      "low": 0.2187,
      "close": 0.2188,
      "volume": 8189.0
    },
    {
      "timestamp": 1762974060000,
      "open": 0.2188,
      "high": 0.219,
      "low": 0.2188,
      "close": 0.2189,
      "volume": 6336.0
    },
    {
      "timestamp": 1762974120000,
      "open": 0.2188,
      "high": 0.2188,
      "low": 0.2187,
      "close": 0.2187,
      "volume": 15440.0
    },
    {
      "timestamp": 1762974180000,
      "open": 0.2188,
      "high": 0.2189,
      "low": 0.2188,
      "close": 0.2189,
      "volume": 2374.0
    },
    {
      "timestamp": 1762974240000,
      "open": 0.2188,
      "high": 0.2188,
      "low": 0.2185,
      "close": 0.2185,
      "volume": 3517.0
    },
    {
      "timestamp": 1762974300000,
      "open": 0.2184,
      "high": 0.2184,
      "low": 0.2179,
      "close": 0.2181,
      "volume": 84423.0
    },
    {
      "timestamp": 1762974360000,
      "open": 0.218,
      "high": 0.2181,
      "low": 0.218,
      "close": 0.2181,
      "volume": 550.0
    },
    {
      "timestamp": 1762974420000,
      "open": 0.218,
      "high": 0.218,
      "low": 0.2171,
      "close": 0.2174,
      "volume": 23178.0
    },
    {
      "timestamp": 1762974480000,
      "open": 0.2175,
      "high": 0.2178,
      "low": 0.2175,
      "close": 0.2176,
      "volume": 28369.0
    },
    {
      "timestamp": 1762974540000,
      "open": 0.2176,
      "high": 0.2177,
      "low": 0.2175,
      "close": 0.2176,
      "volume": 13726.0
    },
    {
      "timestamp": 1762974600000,
      "open": 0.2177,
      "high": 0.2177,
      "low": 0.2172,
      "close": 0.2175,
      "volume": 5782.0
    },
    {
      "timestamp": 1762974660000,
      "open": 0.2174,
      "high": 0.2174,
      "low": 0.2171,
      "close": 0.2171,
      "volume": 2856.0
    },
    {
      "timestamp": 1762974720000,
      "open": 0.2171,
      "high": 0.2172,
      "low": 0.2171,
      "close": 0.2172,
      "volume": 21215.0
    },
    {
      "timestamp": 1762974780000,
      "open": 0.2172,
      "high": 0.2172,
      "low": 0.2171,
      "close": 0.2171,
      "volume": 2219.0
    },
    {
      "timestamp": 1762974840000,
      "open": 0.2171,
      "high": 0.2171,
      "low": 0.2168,
      "close": 0.2169,
      "volume": 8558.0
    },
    {
      "timestamp": 1762974900000,
      "open": 0.217,
      "high": 0.2171,
      "low": 0.217,
      "close": 0.217,
      "volume": 1096.0
    },
    {
      "timestamp": 1762974960000,
      "open": 0.2171,
      "high": 0.2174,
      "low": 0.2171,
      "close": 0.2172,
      "volume": 8798.0
    },
    {
      "timestamp": 1762975020000,
      "open": 0.2172,
      "high": 0.2172,
      "low": 0.2172,
      "close": 0.2172,
      "volume": 5746.0
    },
    {
      "timestamp": 1762975080000,
      "open": 0.2172,
      "high": 0.2172,
      "low": 0.2168,
      "close": 0.2168,
      "volume": 8753.0
    },
    {
      "timestamp": 1762975140000,
      "open": 0.2168,
      "high": 0.2171,
      "low": 0.2168,
      "close": 0.217,
      "volume": 11171.0
    },
    {
      "timestamp": 1762975200000,
      "open": 0.2171,
      "high": 0.2172,
      "low": 0.217,
      "close": 0.217,
      "volume": 4641.0
    },
    {
      "timestamp": 1762975260000,
      "open": 0.2169,
      "high": 0.2171,
      "low": 0.2169,
      "close": 0.217,
      "volume": 2692.0
    },
    {
      "timestamp": 1762975320000,
      "open": 0.217,
      "high": 0.2174,
      "low": 0.217,
      "close": 0.2174,
      "volume": 9489.0
    },
    {
      "timestamp": 1762975380000,
      "open": 0.2175,
      "high": 0.2176,
      "low": 0.2175,
      "close": 0.2176,
      "volume": 3834.0
    },
    {
      "timestamp": 1762975440000,
      "open": 0.2176,
      "high": 0.2176,
      "low": 0.2173,
      "close": 0.2173,
      "volume": 2091.0
    },
    {
      "timestamp": 1762975500000,
      "open": 0.2173,
      "high": 0.2173,
      "low": 0.2173,
      "close": 0.2173,
      "volume": 951.0
    },
    {
      "timestamp": 1762975560000,
      "open": 0.2172,
      "high": 0.2173,
      "low": 0.2172,
      "close": 0.2173,
      "volume": 2788.0
    },
    {
      "timestamp": 1762975620000,
      "open": 0.2172,
      "high": 0.2172,
      "low": 0.217,
      "close": 0.217,
      "volume": 5504.0
    },
    {
      "timestamp": 1762975680000,
      "open": 0.217,
      "high": 0.217,
      "low": 0.2161,
      "close": 0.2165,
      "volume": 23359.0
    },
    {
      "timestamp": 1762975740000,
      "open": 0.2166,
      "high": 0.2168,
      "low": 0.2166,
      "close": 0.2167,
      "volume": 3614.0
    },
    {
      "timestamp": 1762975800000,
      "open": 0.2167,
      "high": 0.217,
      "low": 0.2167,
      "close": 0.2168,
      "volume": 14688.0
    },
    {
      "timestamp": 1762975860000,
      "open": 0.2168,
      "high": 0.217,
      "low": 0.2163,
      "close": 0.2163,
      "volume": 2317.0
    },
    {
      "timestamp": 1762975920000,
      "open": 0.2162,
      "high": 0.2162,
      "low": 0.2156,
      "close": 0.2159,
      "volume": 50922.0
    },
    {
      "timestamp": 1762975980000,
      "open": 0.2158,
      "high": 0.2158,
      "low": 0.2156,
      "close": 0.2157,
      "volume": 4483.0
    },
    {
      "timestamp": 1762976040000,
      "open": 0.2158,
      "high": 0.2161,
      "low": 0.2158,
      "close": 0.2161,
      "volume": 2657.0
    },
    {
      "timestamp": 1762976100000,
      "open": 0.216,
      "high": 0.2161,
      "low": 0.2159,
      "close": 0.2159,
      "volume": 14186.0
    },
    {
      "timestamp": 1762976160000,
      "open": 0.2162,
      "high": 0.2163,
      "low": 0.2162,
      "close": 0.2162,
      "volume": 585.0
    },
    {
      "timestamp": 1762976220000,
      "open": 0.2163,
      "high": 0.2163,
      "low": 0.216,
      "close": 0.216,
      "volume": 3414.0
    },
    {
      "timestamp": 1762976280000,
      "open": 0.2161,
      "high": 0.2161,
      "low": 0.216,
      "close": 0.216,
      "volume": 1636.0
    },
    {
      "timestamp": 1762976340000,
      "open": 0.2159,
      "high": 0.2165,
      "low": 0.2159,
      "close": 0.2165,
      "volume": 2014.0
    },
    {
      "timestamp": 1762976400000,
      "open": 0.2166,
      "high": 0.2169,
      "low": 0.2163,
      "close": 0.2169,
      "volume": 8983.0
    },
    {
      "timestamp": 1762976460000,
      "open": 0.217,
      "high": 0.2175,
      "low": 0.217,
      "close": 0.2175,
      "volume": 8607.0
    },
    {
      "timestamp": 1762976520000,
      "open": 0.2174,
      "high": 0.2178,
      "low": 0.2172,
      "close": 0.2178,
      "volume": 18061.0
    },
    {
      "timestamp": 1762976580000,
      "open": 0.2178,
      "high": 0.219,
      "low": 0.2178,
      "close": 0.2189,
      "volume": 151570.0
    },
    {
      "timestamp": 1762976640000,
      "open": 0.2189,
      "high": 0.2189,
      "low": 0.2177,
      "close": 0.2177,
      "volume": 1990.0
    },
    {
      "timestamp": 1762976700000,
      "open": 0.2179,
      "high": 0.2179,
      "low": 0.2177,
      "close": 0.2177,
      "volume": 411.0
    },
    {
      "timestamp": 1762976760000,
      "open": 0.2178,
      "high": 0.2178,
      "low": 0.2174,
      "close": 0.2174,
      "volume": 27085.0
    },
    {
      "timestamp": 1762976820000,
      "open": 0.2176,
      "high": 0.2176,
      "low": 0.2173,
      "close": 0.2173,
      "volume": 3762.0
    },
    {
      "timestamp": 1762976880000,
      "open": 0.2173,
      "high": 0.2175,
      "low": 0.2173,
      "close": 0.2175,
      "volume": 1594.0
    },
    {
      "timestamp": 1762976940000,
      "open": 0.2174,
      "high": 0.2176,
      "low": 0.2174,
      "close": 0.2176,
      "volume": 9912.0
    },
    {
      "timestamp": 1762977000000,
      "open": 0.2176,
      "high": 0.2177,
      "low": 0.2176,
      "close": 0.2176,
      "volume": 1374.0
    },
    {
      "timestamp": 1762977060000,
      "open": 0.2175,
      "high": 0.2177,
      "low": 0.2175,
      "close": 0.2176,
      "volume": 1828.0
    },
    {
      "timestamp": 1762977120000,
      "open": 0.2177,
      "high": 0.218,
      "low": 0.2177,
      "close": 0.218,
      "volume": 826.0
    },
    {
      "timestamp": 1762977180000,
      "open": 0.2181,
      "high": 0.2183,
      "low": 0.2181,
      "close": 0.2181,
      "volume": 5382.0
    },
    {
      "timestamp": 1762977240000,
      "open": 0.218,
      "high": 0.2182,
      "low": 0.218,
      "close": 0.2182,
      "volume": 2051.0
    },
    {
      "timestamp": 1762977300000,
      "open": 0.2182,
      "high": 0.2182,
      "low": 0.2181,
      "close": 0.2181,
      "volume": 4515.0
    },
    {
      "timestamp": 1762977360000,
      "open": 0.2182,
      "high": 0.2184,
      "low": 0.2181,
      "close": 0.2184,
      "volume": 1193.0
    },
    {
      "timestamp": 1762977420000,
      "open": 0.2184,
      "high": 0.2184,
      "low": 0.2184,
      "close": 0.2184,
      "volume": 594.0
    },
    {
      "timestamp": 1762977480000,
      "open": 0.2184,
      "high": 0.2184,
      "low": 0.2182,
      "close": 0.2182,
      "volume": 661.0
    },
    {
      "timestamp": 1762977540000,
      "open": 0.2181,
      "high": 0.2181,
      "low": 0.218,
      "close": 0.218,
      "volume": 4685.0
    },
    {
      "timestamp": 1762977600000,
      "open": 0.2179,
      "high": 0.218,
      "low": 0.2177,
      "close": 0.2178,
      "volume": 2825.0
    },
    {
      "timestamp": 1762977660000,
      "open": 0.2179,
      "high": 0.2182,
      "low": 0.2179,
      "close": 0.2179,
      "volume": 5924.0
    },
    {
      "timestamp": 1762977720000,
      "open": 0.218,
      "high": 0.218,
      "low": 0.2176,
      "close": 0.2178,
      "volume": 4317.0
    },
    {
      "timestamp": 1762977780000,
      "open": 0.2179,
      "high": 0.2183,
      "low": 0.2179,
      "close": 0.2181,
      "volume": 3342.0
    },
    {
      "timestamp": 1762977840000,
      "open": 0.218,
      "high": 0.2186,
      "low": 0.218,
      "close": 0.2186,
      "volume": 20137.0
    },
    {
      "timestamp": 1762977900000,
      "open": 0.2186,
      "high": 0.2186,
      "low": 0.2183,
      "close": 0.2184,
      "volume": 6822.0
    },
    {
      "timestamp": 1762977960000,
      "open": 0.2184,
      "high": 0.2187,
      "low": 0.2184,
      "close": 0.2187,
      "volume": 5975.0
    },
    {
      "timestamp": 1762978020000,
      "open": 0.2187,
      "high": 0.219,
      "low": 0.2187,
      "close": 0.219,
      "volume": 6015.0
    },
    {
      "timestamp": 1762978080000,
      "open": 0.219,
      "high": 0.2193,
      "low": 0.2188,
      "close": 0.2193,
      "volume": 9683.0
    },
    {
      "timestamp": 1762978140000,
      "open": 0.2194,
      "high": 0.2197,
      "low": 0.2194,
      "close": 0.2195,
      "volume": 15035.0
    },
    {
      "timestamp": 1762978200000,
      "open": 0.2195,
      "high": 0.2196,
      "low": 0.2193,
      "close": 0.2193,
      "volume": 7523.0
    },
    {
      "timestamp": 1762978260000,
      "open": 0.2194,
      "high": 0.2197,
      "low": 0.2194,
      "close": 0.2196,
      "volume": 1981.0
    },
    {
      "timestamp": 1762978320000,
      "open": 0.2195,
      "high": 0.2195,
      "low": 0.2193,
      "close": 0.2193,
      "volume": 138.0
    },
    {
      "timestamp": 1762978380000,
      "open": 0.2192,
      "high": 0.2193,
      "low": 0.219,
      "close": 0.219,
      "volume": 2923.0
    },
    {
      "timestamp": 1762978440000,
      "open": 0.2189,
      "high": 0.219,
      "low": 0.2188,
      "close": 0.219,
      "volume": 2563.0
    },
    {
      "timestamp": 1762978500000,
      "open": 0.2191,
      "high": 0.2194,
      "low": 0.2191,
      "close": 0.2193,
      "volume": 1219.0
    },
    {
      "timestamp": 1762978560000,
      "open": 0.2193,
      "high": 0.2193,
      "low": 0.2189,
      "close": 0.2193,
      "volume": 16438.0
    },
    {
      "timestamp": 1762978620000,
      "open": 0.2193,
      "high": 0.2195,
      "low": 0.2193,
      "close": 0.2194,
      "volume": 32393.0
    },
    {
      "timestamp": 1762978680000,
      "open": 0.2195,
      "high": 0.2198,
      "low": 0.2195,
      "close": 0.2198,
      "volume": 4449.0
    },
    {
      "timestamp": 1762978740000,
      "open": 0.2198,
      "high": 0.2199,
      "low": 0.2198,
      "close": 0.2199,
      "volume": 5268.0
    },
    {
      "timestamp": 1762978800000,
      "open": 0.2199,
      "high": 0.2199,
      "low": 0.2198,
      "close": 0.2199,
      "volume": 2878.0
    },
    {
      "timestamp": 1762978860000,
      "open": 0.2199,
      "high": 0.2204,
      "low": 0.2199,
      "close": 0.2204,
      "volume": 3299.0
    },
    {
      "timestamp": 1762978920000,
      "open": 0.2204,
      "high": 0.2206,
      "low": 0.2204,
      "close": 0.2204,
      "volume": 1065.0
    },
    {
      "timestamp": 1762978980000,
      "open": 0.2204,
      "high": 0.2204,
      "low": 0.22,
      "close": 0.2201,
      "volume": 2941.0
    },
    {
      "timestamp": 1762979040000,
      "open": 0.2202,
      "high": 0.2204,
      "low": 0.2202,
      "close": 0.2204,
      "volume": 3144.0
    },
    {
      "timestamp": 1762979100000,
      "open": 0.2205,
      "high": 0.2207,
      "low": 0.2205,
      "close": 0.2207,
      "volume": 403.0
    },
    {
      "timestamp": 1762979160000,
      "open": 0.2208,
      "high": 0.2213,
      "low": 0.2208,
      "close": 0.2213,
      "volume": 13888.0
    },
    {
      "timestamp": 1762979220000,
      "open": 0.2211,
      "high": 0.2211,
      "low": 0.2209,
      "close": 0.221,
      "volume": 15696.0
    },
    {
      "timestamp": 1762979280000,
      "open": 0.2211,
      "high": 0.2211,
      "low": 0.2211,
      "close": 0.2211,
      "volume": 743.0
    },
    {
      "timestamp": 1762979340000,
      "open": 0.2211,
      "high": 0.2211,
      "low": 0.2211,
      "close": 0.2211,
      "volume": 937.0
    },
    {
      "timestamp": 1762979400000,
      "open": 0.2211,
      "high": 0.2214,
      "low": 0.2211,
      "close": 0.2213,
      "volume": 1098.0
    },
    {
      "timestamp": 1762979460000,
      "open": 0.2213,
      "high": 0.2215,
      "low": 0.2212,
      "close": 0.2215,
      "volume": 1658.0
    },
    {
      "timestamp": 1762979520000,
      "open": 0.2216,
      "high": 0.2218,
      "low": 0.2216,
      "close": 0.2218,
      "volume": 1307.0
    },
    {
      "timestamp": 1762979580000,
      "open": 0.2219,
      "high": 0.2225,
      "low": 0.2219,
      "close": 0.2219,
      "volume": 41099.0
    },
    {
      "timestamp": 1762979640000,
      "open": 0.2218,
      "high": 0.2219,
      "low": 0.2217,
      "close": 0.2219,
      "volume": 7261.0
    },
    {
      "timestamp": 1762979700000,
      "open": 0.2219,
      "high": 0.2219,
      "low": 0.2218,
      "close": 0.2218,
      "volume": 3628.0
    },
    {
      "timestamp": 1762979760000,
      "open": 0.2217,
      "high": 0.2217,
      "low": 0.2212,
      "close": 0.2212,
      "volume": 2450.0
    },
    {
      "timestamp": 1762979820000,
      "open": 0.2213,
      "high": 0.2214,
      "low": 0.2213,
      "close": 0.2214,
      "volume": 2965.0
    },
    {
      "timestamp": 1762979880000,
      "open": 0.2213,
      "high": 0.2215,
      "low": 0.2212,
      "close": 0.2214,
      "volume": 1714.0
    },
    {
      "timestamp": 1762979940000,
      "open": 0.2214,
      "high": 0.2217,
      "low": 0.2214,
      "close": 0.2217,
      "volume": 5064.0
    },
    {
      "timestamp": 1762980000000,
      "open": 0.2218,
      "high": 0.222,
      "low": 0.2218,
      "close": 0.222,
      "volume": 865.0
    },
    {
      "timestamp": 1762980060000,
      "open": 0.222,
      "high": 0.222,
      "low": 0.2219,
      "close": 0.2219,
      "volume": 1150.0
    },
    {
      "timestamp": 1762980120000,
      "open": 0.2219,
      "high": 0.2223,
      "low": 0.2219,
      "close": 0.2223,
      "volume": 23994.0
    },
    {
      "timestamp": 1762980180000,
      "open": 0.2222,
      "high": 0.2223,
      "low": 0.2221,
      "close": 0.2221,
      "volume": 2688.0
    },
    {
      "timestamp": 1762980240000,
      "open": 0.2221,
      "high": 0.2221,
      "low": 0.2218,
      "close": 0.222,
      "volume": 4816.0
    },
    {
      "timestamp": 1762980300000,
      "open": 0.222,
      "high": 0.2222,
      "low": 0.222,
      "close": 0.2221,
      "volume": 6330.0
    },
    {
      "timestamp": 1762980360000,
      "open": 0.222,
      "high": 0.222,
      "low": 0.2218,
      "close": 0.2218,
      "volume": 840.0
    },
    {
      "timestamp": 1762980420000,
      "open": 0.2218,
      "high": 0.2218,
      "low": 0.2217,
      "close": 0.2217,
      "volume": 743.0
    },
    {
      "timestamp": 1762980480000,
      "open": 0.2216,
      "high": 0.2216,
      "low": 0.2215,
      "close": 0.2216,
      "volume": 2885.0
    },
    {
      "timestamp": 1762980540000,
      "open": 0.2216,
      "high": 0.2216,
      "low": 0.2216,
      "close": 0.2216,
      "volume": 7865.0
    },
    {
      "timestamp": 1762980600000,
      "open": 0.2217,
      "high": 0.2218,
      "low": 0.2217,
      "close": 0.2217,
      "volume": 8343.0
    },
    {
      "timestamp": 1762980660000,
      "open": 0.2217,
      "high": 0.2217,
      "low": 0.2216,
      "close": 0.2216,
      "volume": 4368.0
    },
    {
      "timestamp": 1762980720000,
      "open": 0.2216,
      "high": 0.2217,
      "low": 0.2214,
      "close": 0.2216,
      "volume": 10533.0
    },
    {
      "timestamp": 1762980780000,
      "open": 0.2217,
      "high": 0.2219,
      "low": 0.2217,
      "close": 0.2218,
      "volume": 5804.0
    },
    {
      "timestamp": 1762980840000,
      "open": 0.2217,
      "high": 0.2217,
      "low": 0.2215,
      "close": 0.2215,
      "volume": 3644.0
    },
    {
      "timestamp": 1762980900000,
      "open": 0.2215,
      "high": 0.2215,
      "low": 0.2214,
      "close": 0.2214,
      "volume": 510.0
    },
    {
      "timestamp": 1762980960000,
      "open": 0.2214,
      "high": 0.2214,
      "low": 0.2214,
      "close": 0.2214,
      "volume": 6055.0
    },
    {
      "timestamp": 1762981020000,
      "open": 0.2213,
      "high": 0.2213,
      "low": 0.2213,
      "close": 0.2213,
      "volume": 791.0
    },
    {
      "timestamp": 1762981080000,
      "open": 0.2213,
      "high": 0.2213,
      "low": 0.2211,
      "close": 0.2211,
      "volume": 1486.0
    },
    {
      "timestamp": 1762981140000,
      "open": 0.221,
      "high": 0.2211,
      "low": 0.2209,
      "close": 0.2211,
      "volume": 57424.0
    },
    {
      "timestamp": 1762981200000,
      "open": 0.2212,
      "high": 0.2213,
      "low": 0.2212,
      "close": 0.2212,
      "volume": 1415.0
    },
    {
      "timestamp": 1762981260000,
      "open": 0.2213,
      "high": 0.2213,
      "low": 0.2213,
      "close": 0.2213,
      "volume": 468.0
    },
    {
      "timestamp": 1762981320000,
      "open": 0.2214,
      "high": 0.2214,
      "low": 0.2213,
      "close": 0.2214,
      "volume": 383.0
    },
    {
      "timestamp": 1762981380000,
      "open": 0.2214,
      "high": 0.2214,
      "low": 0.2212,
      "close": 0.2212,
      "volume": 789.0
    },
    {
      "timestamp": 1762981440000,
      "open": 0.2211,
      "high": 0.2211,
      "low": 0.2206,
      "close": 0.2206,
      "volume": 4775.0
    },
    {
      "timestamp": 1762981500000,
      "open": 0.2207,
      "high": 0.2207,
      "low": 0.2205,
      "close": 0.2206,
      "volume": 2801.0
    },
    {
      "timestamp": 1762981560000,
      "open": 0.2207,
      "high": 0.2207,
      "low": 0.2205,
      "close": 0.2205,
      "volume": 5455.0
    },
    {
      "timestamp": 1762981620000,
      "open": 0.2205,
      "high": 0.2205,
      "low": 0.2204,
      "close": 0.2204,
      "volume": 1755.0
    },
    {
      "timestamp": 1762981680000,
      "open": 0.2203,
      "high": 0.2206,
      "low": 0.2203,
      "close": 0.2205,
      "volume": 3068.0
    },
    {
      "timestamp": 1762981740000,
      "open": 0.2205,
      "high": 0.2206,
      "low": 0.2204,
      "close": 0.2204,
      "volume": 2713.0
    },
    {
      "timestamp": 1762981800000,
      "open": 0.2206,
      "high": 0.2207,
      "low": 0.2206,
      "close": 0.2207,
      "volume": 1663.0
    },
    {
      "timestamp": 1762981860000,
      "open": 0.2207,
      "high": 0.2209,
      "low": 0.2207,
      "close": 0.2209,
      "volume": 20808.0
    },
    {
      "timestamp": 1762981920000,
      "open": 0.2209,
      "high": 0.2213,
      "low": 0.2209,
      "close": 0.2212,
      "volume": 3386.0
    },
    {
      "timestamp": 1762981980000,
      "open": 0.2213,
      "high": 0.2214,
      "low": 0.2213,
      "close": 0.2213,
      "volume": 1014.0
    },
    {
      "timestamp": 1762982040000,
      "open": 0.2212,
      "high": 0.2214,
      "low": 0.2212,
      "close": 0.2214,
      "volume": 633.0
    },
    {
      "timestamp": 1762982100000,
      "open": 0.2213,
      "high": 0.2213,
      "low": 0.2211,
      "close": 0.2212,
      "volume": 1584.0
    },
    {
      "timestamp": 1762982160000,
      "open": 0.2211,
      "high": 0.2211,
      "low": 0.2207,
      "close": 0.2207,
      "volume": 17570.0
    },
    {
      "timestamp": 1762982220000,
      "open": 0.2206,
      "high": 0.2206,
      "low": 0.2206,
      "close": 0.2206,
      "volume": 76.0
    },
    {
      "timestamp": 1762982280000,
      "open": 0.2205,
      "high": 0.2209,
      "low": 0.2205,
      "close": 0.2209,
      "volume": 15179.0
    },
    {
      "timestamp": 1762982340000,
      "open": 0.2209,
      "high": 0.2211,
      "low": 0.2209,
      "close": 0.2211,
      "volume": 815.0
    },
    {
      "timestamp": 1762982400000,
      "open": 0.221,
      "high": 0.221,
      "low": 0.221,
      "close": 0.221,
      "volume": 697.0
    },
    {
      "timestamp": 1762982460000,
      "open": 0.2211,
      "high": 0.2212,
      "low": 0.221,
      "close": 0.2212,
      "volume": 2616.0
    },
    {
      "timestamp": 1762982520000,
      "open": 0.2211,
      "high": 0.2211,
      "low": 0.2211,
      "close": 0.2211,
      "volume": 46.0
    },
    {
      "timestamp": 1762982580000,
      "open": 0.2212,
      "high": 0.2213,
      "low": 0.2212,
      "close": 0.2213,
      "volume": 8014.0
    },
    {
      "timestamp": 1762982640000,
      "open": 0.2211,
      "high": 0.2211,
      "low": 0.221,
      "close": 0.2211,
      "volume": 7728.0
    },
    {
      "timestamp": 1762982700000,
      "open": 0.2209,
      "high": 0.2209,
      "low": 0.2209,
      "close": 0.2209,
      "volume": 46.0
    },
    {
      "timestamp": 1762982760000,
      "open": 0.2209,
      "high": 0.2209,
      "low": 0.2208,
      "close": 0.2209,
      "volume": 9322.0
    },
    {
      "timestamp": 1762982820000,
      "open": 0.2208,
      "high": 0.2209,
      "low": 0.2208,
      "close": 0.2209,
      "volume": 400.0
    },
    {
      "timestamp": 1762982880000,
      "open": 0.2208,
      "high": 0.2208,
      "low": 0.2208,
      "close": 0.2208,
      "volume": 203.0
    },
    {
      "timestamp": 1762982940000,
      "open": 0.221,
      "high": 0.221,
      "low": 0.2209,
      "close": 0.2209,
      "volume": 2534.0
    },
    {
      "timestamp": 1762983000000,
      "open": 0.221,
      "high": 0.221,
      "low": 0.2209,
      "close": 0.221,
      "volume": 4778.0
    },
    {
      "timestamp": 1762983060000,
      "open": 0.2211,
      "high": 0.2212,
      "low": 0.2211,
      "close": 0.2212,
      "volume": 451.0
    },
    {
      "timestamp": 1762983120000,
      "open": 0.2213,
      "high": 0.2215,
      "low": 0.2213,
      "close": 0.2215,
      "volume": 2002.0
    },
    {
      "timestamp": 1762983180000,
      "open": 0.2216,
      "high": 0.2218,
      "low": 0.2216,
      "close": 0.2218,
      "volume": 1032.0
    },
    {
      "timestamp": 1762983240000,
      "open": 0.2217,
      "high": 0.2217,
      "low": 0.2217,
      "close": 0.2217,
      "volume": 1440.0
    },
    {
      "timestamp": 1762983300000,
      "open": 0.2216,
      "high": 0.2216,
      "low": 0.2215,
      "close": 0.2215,
      "volume": 786.0
    },
    {
      "timestamp": 1762983360000,
      "open": 0.2214,
      "high": 0.2214,
      "low": 0.2212,
      "close": 0.2212,
      "volume": 105.0
    },
    {
      "timestamp": 1762983420000,
      "open": 0.2212,
      "high": 0.2212,
      "low": 0.2212,
      "close": 0.2212,
      "volume": 0.0
    },
    {
      "timestamp": 1762983480000,
      "open": 0.2214,
      "high": 0.2216,
      "low": 0.2214,
      "close": 0.2216,
      "volume": 2111.0
    },
    {
      "timestamp": 1762983540000,
      "open": 0.2216,
      "high": 0.2216,
      "low": 0.2216,
      "close": 0.2216,
      "volume": 214.0
    },
    {
      "timestamp": 1762983600000,
      "open": 0.2214,
      "high": 0.2214,
      "low": 0.2213,
      "close": 0.2213,
      "volume": 1120.0
    },
    {
      "timestamp": 1762983660000,
      "open": 0.2214,
      "high": 0.2215,
      "low": 0.2213,
      "close": 0.2213,
      "volume": 968.0
    },
    {
      "timestamp": 1762983720000,
      "open": 0.2212,
      "high": 0.2212,
      "low": 0.2211,
      "close": 0.2211,
      "volume": 1288.0
    },
    {
      "timestamp": 1762983780000,
      "open": 0.2211,
      "high": 0.2211,
      "low": 0.2211,
      "close": 0.2211,
      "volume": 776.0
    },
    {
      "timestamp": 1762983840000,
      "open": 0.2212,
      "high": 0.2213,
      "low": 0.2212,
      "close": 0.2213,
      "volume": 92.0
    },
    {
      "timestamp": 1762983900000,
      "open": 0.2212,
      "high": 0.2213,
      "low": 0.2212,
      "close": 0.2212,
      "volume": 984.0
    },
    {
      "timestamp": 1762983960000,
      "open": 0.2211,
      "high": 0.2213,
      "low": 0.2211,
      "close": 0.2213,
      "volume": 383.0
    },
    {
      "timestamp": 1762984020000,
      "open": 0.2211,
      "high": 0.2211,
      "low": 0.2211,
      "close": 0.2211,
      "volume": 743.0
    },
    {
      "timestamp": 1762984080000,
      "open": 0.2211,
      "high": 0.2211,
      "low": 0.221,
      "close": 0.221,
      "volume": 7736.0
    },
    {
      "timestamp": 1762984140000,
      "open": 0.221,
      "high": 0.2211,
      "low": 0.221,
      "close": 0.2211,
      "volume": 1816.0
    },
    {
      "timestamp": 1762984200000,
      "open": 0.2211,
      "high": 0.2211,
      "low": 0.2211,
      "close": 0.2211,
      "volume": 210.0
    },
    {
      "timestamp": 1762984260000,
      "open": 0.221,
      "high": 0.221,
      "low": 0.221,
      "close": 0.221,
      "volume": 909.0
    },
    {
      "timestamp": 1762984320000,
      "open": 0.221,
      "high": 0.221,
      "low": 0.221,
      "close": 0.221,
      "volume": 723.0
    },
    {
      "timestamp": 1762984380000,
      "open": 0.2211,
      "high": 0.2213,
      "low": 0.2211,
      "close": 0.2213,
      "volume": 1517.0
    },
    {
      "timestamp": 1762984440000,
      "open": 0.2213,
      "high": 0.2213,
      "low": 0.2213,
      "close": 0.2213,
      "volume": 2297.0
    },
    {
      "timestamp": 1762984500000,
      "open": 0.2212,
      "high": 0.2212,
      "low": 0.2209,
      "close": 0.2209,
      "volume": 6934.0
    },
    {
      "timestamp": 1762984560000,
      "open": 0.221,
      "high": 0.2216,
      "low": 0.221,
      "close": 0.2216,
      "volume": 13503.0
    },
    {
      "timestamp": 1762984620000,
      "open": 0.2216,
      "high": 0.2216,
      "low": 0.2215,
      "close": 0.2216,
      "volume": 3485.0
    },
    {
      "timestamp": 1762984680000,
      "open": 0.2215,
      "high": 0.2215,
      "low": 0.2213,
      "close": 0.2215,
      "volume": 2351.0
    },
    {
      "timestamp": 1762984740000,
      "open": 0.2216,
      "high": 0.2216,
      "low": 0.2216,
      "close": 0.2216,
      "volume": 46.0
    },
    {
      "timestamp": 1762984800000,
      "open": 0.2215,
      "high": 0.2215,
      "low": 0.2213,
      "close": 0.2213,
      "volume": 345.0
    },
    {
      "timestamp": 1762984860000,
      "open": 0.2213,
      "high": 0.2213,
      "low": 0.2213,
      "close": 0.2213,
      "volume": 697.0
    },
    {
      "timestamp": 1762984920000,
      "open": 0.2212,
      "high": 0.2214,
      "low": 0.2212,
      "close": 0.2214,
      "volume": 2981.0
    },
    {
      "timestamp": 1762984980000,
      "open": 0.2215,
      "high": 0.2216,
      "low": 0.2215,
      "close": 0.2216,
      "volume": 1391.0
    },
    {
      "timestamp": 1762985040000,
      "open": 0.2214,
      "high": 0.2214,
      "low": 0.2213,
      "close": 0.2214,
      "volume": 284.0
    },
    {
      "timestamp": 1762985100000,
      "open": 0.2214,
      "high": 0.2214,
      "low": 0.2213,
      "close": 0.2213,
      "volume": 949.0
    },
    {
      "timestamp": 1762985160000,
      "open": 0.2212,
      "high": 0.2212,
      "low": 0.221,
      "close": 0.221,
      "volume": 2339.0
    },
    {
      "timestamp": 1762985220000,
      "open": 0.221,
      "high": 0.221,
      "low": 0.2208,
      "close": 0.2208,
      "volume": 7960.0
    },
    {
      "timestamp": 1762985280000,
      "open": 0.2207,
      "high": 0.2207,
      "low": 0.2206,
      "close": 0.2206,
      "volume": 2358.0
    },
    {
      "timestamp": 1762985340000,
      "open": 0.2205,
      "high": 0.2205,
      "low": 0.2204,
      "close": 0.2205,
      "volume": 1929.0
    },
    {
      "timestamp": 1762985400000,
      "open": 0.2206,
      "high": 0.2206,
      "low": 0.2204,
      "close": 0.2205,
      "volume": 4889.0
    },
    {
      "timestamp": 1762985460000,
      "open": 0.2206,
      "high": 0.2206,
      "low": 0.2206,
      "close": 0.2206,
      "volume": 27.0
    },
    {
      "timestamp": 1762985520000,
      "open": 0.2206,
      "high": 0.2209,
      "low": 0.2206,
      "close": 0.2209,
      "volume": 6841.0
    },
    {
      "timestamp": 1762985580000,
      "open": 0.2209,
      "high": 0.2209,
      "low": 0.2207,
      "close": 0.2208,
      "volume": 4107.0
    },
    {
      "timestamp": 1762985640000,
      "open": 0.2203,
      "high": 0.2203,
      "low": 0.2203,
      "close": 0.2203,
      "volume": 895.0
    },
    {
      "timestamp": 1762985700000,
      "open": 0.2205,
      "high": 0.2206,
      "low": 0.2203,
      "close": 0.2206,
      "volume": 3673.0
    },
    {
      "timestamp": 1762985760000,
      "open": 0.2205,
      "high": 0.2206,
      "low": 0.2205,
      "close": 0.2206,
      "volume": 1987.0
    },
    {
      "timestamp": 1762985820000,
      "open": 0.2206,
      "high": 0.2208,
      "low": 0.2206,
      "close": 0.2208,
      "volume": 893.0
    },
    {
      "timestamp": 1762985880000,
      "open": 0.2203,
      "high": 0.2203,
      "low": 0.2202,
      "close": 0.2203,
      "volume": 4006.0
    },
    {
      "timestamp": 1762985940000,
      "open": 0.2203,
      "high": 0.2203,
      "low": 0.2203,
      "close": 0.2203,
      "volume": 891.0
    },
    {
      "timestamp": 1762986000000,
      "open": 0.2203,
      "high": 0.2203,
      "low": 0.2203,
      "close": 0.2203,
      "volume": 697.0
    },
    {
      "timestamp": 1762986060000,
      "open": 0.2202,
      "high": 0.2203,
      "low": 0.2202,
      "close": 0.2203,
      "volume": 423.0
    },
    {
      "timestamp": 1762986120000,
      "open": 0.2204,
      "high": 0.2209,
      "low": 0.2204,
      "close": 0.2208,
      "volume": 5007.0
    },
    {
      "timestamp": 1762986180000,
      "open": 0.2208,
      "high": 0.2208,
      "low": 0.2208,
      "close": 0.2208,
      "volume": 130.0
    },
    {
      "timestamp": 1762986240000,
      "open": 0.2209,
      "high": 0.2211,
      "low": 0.2209,
      "close": 0.2211,
      "volume": 862.0
    },
    {
      "timestamp": 1762986300000,
      "open": 0.2211,
      "high": 0.2211,
      "low": 0.221,
      "close": 0.221,
      "volume": 1079.0
    },
    {
      "timestamp": 1762986360000,
      "open": 0.221,
      "high": 0.221,
      "low": 0.221,
      "close": 0.221,
      "volume": 0.0
    },
    {
      "timestamp": 1762986420000,
      "open": 0.221,
      "high": 0.2212,
      "low": 0.221,
      "close": 0.2212,
      "volume": 1130.0
    },
    {
      "timestamp": 1762986480000,
      "open": 0.2209,
      "high": 0.2209,
      "low": 0.2209,
      "close": 0.2209,
      "volume": 1150.0
    },
    {
      "timestamp": 1762986540000,
      "open": 0.2207,
      "high": 0.2207,
      "low": 0.2207,
      "close": 0.2207,
      "volume": 11965.0
    },
    {
      "timestamp": 1762986600000,
      "open": 0.2206,
      "high": 0.2206,
      "low": 0.2206,
      "close": 0.2206,
      "volume": 38.0
    },
    {
      "timestamp": 1762986660000,
      "open": 0.2205,
      "high": 0.2205,
      "low": 0.2204,
      "close": 0.2204,
      "volume": 771.0
    },
    {
      "timestamp": 1762986720000,
      "open": 0.2206,
      "high": 0.2208,
      "low": 0.2206,
      "close": 0.2208,
      "volume": 1010.0
    },
    {
      "timestamp": 1762986780000,
      "open": 0.2206,
      "high": 0.2206,
      "low": 0.2206,
      "close": 0.2206,
      "volume": 310.0
    },
    {
      "timestamp": 1762986840000,
      "open": 0.2208,
      "high": 0.2209,
      "low": 0.2208,
      "close": 0.2209,
      "volume": 13197.0
    },
    {
      "timestamp": 1762986900000,
      "open": 0.2209,
      "high": 0.2209,
      "low": 0.2209,
      "close": 0.2209,
      "volume": 0.0
    },
    {
      "timestamp": 1762986960000,
      "open": 0.221,
      "high": 0.221,
      "low": 0.221,
      "close": 0.221,
      "volume": 93.0
    },
    {
      "timestamp": 1762987020000,
      "open": 0.221,
      "high": 0.2212,
      "low": 0.221,
      "close": 0.2212,
      "volume": 1157.0
    },
    {
      "timestamp": 1762987080000,
      "open": 0.2212,
      "high": 0.2212,
      "low": 0.2212,
      "close": 0.2212,
      "volume": 135.0
    },
    {
      "timestamp": 1762987140000,
      "open": 0.2212,
      "high": 0.2212,
      "low": 0.2212,
      "close": 0.2212,
      "volume": 0.0
    },
    {
      "timestamp": 1762987200000,
      "open": 0.2212,
      "high": 0.2212,
      "low": 0.2212,
      "close": 0.2212,
      "volume": 0.0
    },
    {
      "timestamp": 1762987260000,
      "open": 0.2214,
      "high": 0.2214,
      "low": 0.2212,
      "close": 0.2214,
      "volume": 9574.0
    },
    {
      "timestamp": 1762987320000,
      "open": 0.2214,
      "high": 0.2214,
      "low": 0.2214,
      "close": 0.2214,
      "volume": 0.0
    },
    {
      "timestamp": 1762987380000,
      "open": 0.2215,
      "high": 0.2215,
      "low": 0.2215,
      "close": 0.2215,
      "volume": 1003.0
    },
    {
      "timestamp": 1762987440000,
      "open": 0.2217,
      "high": 0.2217,
      "low": 0.2217,
      "close": 0.2217,
      "volume": 4474.0
    },
    {
      "timestamp": 1762987500000,
      "open": 0.2217,
      "high": 0.2217,
      "low": 0.2217,
      "close": 0.2217,
      "volume": 192.0
    },
    {
      "timestamp": 1762987560000,
      "open": 0.2218,
      "high": 0.222,
      "low": 0.2218,
      "close": 0.222,
      "volume": 11555.0
    },
    {
      "timestamp": 1762987620000,
      "open": 0.2221,
      "high": 0.2221,
      "low": 0.222,
      "close": 0.2221,
      "volume": 6790.0
    },
    {
      "timestamp": 1762987680000,
      "open": 0.2221,
      "high": 0.2221,
      "low": 0.2218,
      "close": 0.2219,
      "volume": 18054.0
    },
    {
      "timestamp": 1762987740000,
      "open": 0.222,
      "high": 0.222,
      "low": 0.222,
      "close": 0.222,
      "volume": 46.0
    },
    {
      "timestamp": 1762987800000,
      "open": 0.222,
      "high": 0.222,
      "low": 0.222,
      "close": 0.222,
      "volume": 0.0
    },
    {
      "timestamp": 1762987860000,
      "open": 0.2223,
      "high": 0.2225,
      "low": 0.2223,
      "close": 0.2224,
      "volume": 13489.0
    },
    {
      "timestamp": 1762987920000,
      "open": 0.2225,
      "high": 0.2225,
      "low": 0.2225,
      "close": 0.2225,
      "volume": 2691.0
    },
    {
      "timestamp": 1762987980000,
      "open": 0.2225,
      "high": 0.2232,
      "low": 0.2225,
      "close": 0.2232,
      "volume": 33950.0
    },
    {
      "timestamp": 1762988040000,
      "open": 0.2232,
      "high": 0.2238,
      "low": 0.2232,
      "close": 0.2237,
      "volume": 40134.0
    },
    {
      "timestamp": 1762988100000,
      "open": 0.2234,
      "high": 0.2236,
      "low": 0.2232,
      "close": 0.2236,
      "volume": 24190.0
    },
    {
      "timestamp": 1762988160000,
      "open": 0.2236,
      "high": 0.2236,
      "low": 0.2236,
      "close": 0.2236,
      "volume": 0.0
    },
    {
      "timestamp": 1762988220000,
      "open": 0.2236,
      "high": 0.2236,
      "low": 0.2236,
      "close": 0.2236,
      "volume": 0.0
    },
    {
      "timestamp": 1762988280000,
      "open": 0.2233,
      "high": 0.2233,
      "low": 0.2233,
      "close": 0.2233,
      "volume": 500.0
    },
    {
      "timestamp": 1762988340000,
      "open": 0.2233,
      "high": 0.2233,
      "low": 0.2233,
      "close": 0.2233,
      "volume": 0.0
    },
    {
      "timestamp": 1762988400000,
      "open": 0.2228,
      "high": 0.2234,
      "low": 0.2228,
      "close": 0.2234,
      "volume": 131951.0
    },
    {
      "timestamp": 1762988460000,
      "open": 0.2234,
      "high": 0.2235,
      "low": 0.2232,
      "close": 0.2233,
      "volume": 71382.0
    },
    {
      "timestamp": 1762988520000,
      "open": 0.2228,
      "high": 0.2228,
      "low": 0.2228,
      "close": 0.2228,
      "volume": 30.0
    },
    {
      "timestamp": 1762988580000,
      "open": 0.2228,
      "high": 0.2231,
      "low": 0.2228,
      "close": 0.223,
      "volume": 22213.0
    },
    {
      "timestamp": 1762988640000,
      "open": 0.223,
      "high": 0.2232,
      "low": 0.2228,
      "close": 0.2229,
      "volume": 229147.0
    },
    {
      "timestamp": 1762988700000,
      "open": 0.2228,
      "high": 0.2234,
      "low": 0.2228,
      "close": 0.2232,
      "volume": 73981.0
    },
    {
      "timestamp": 1762988760000,
      "open": 0.2232,
      "high": 0.2234,
      "low": 0.2232,
      "close": 0.2234,
      "volume": 23532.0
    },
    {
      "timestamp": 1762988820000,
      "open": 0.2233,
      "high": 0.2233,
      "low": 0.2226,
      "close": 0.2226,
      "volume": 13200.0
    },
    {
      "timestamp": 1762988880000,
      "open": 0.2222,
      "high": 0.2222,
      "low": 0.221,
      "close": 0.2214,
      "volume": 18332.0
    },
    {
      "timestamp": 1762988940000,
      "open": 0.2213,
      "high": 0.2213,
      "low": 0.2198,
      "close": 0.22,
      "volume": 561353.0
    },
    {
      "timestamp": 1762989000000,
      "open": 0.2202,
      "high": 0.2211,
      "low": 0.2202,
      "close": 0.221,
      "volume": 67061.0
    },
    {
      "timestamp": 1762989060000,
      "open": 0.221,
      "high": 0.2213,
      "low": 0.2209,
      "close": 0.2213,
      "volume": 11526.0
    },
    {
      "timestamp": 1762989120000,
      "open": 0.2212,
      "high": 0.2212,
      "low": 0.2209,
      "close": 0.2209,
      "volume": 3384.0
    },
    {
      "timestamp": 1762989180000,
      "open": 0.2208,
      "high": 0.2214,
      "low": 0.2208,
      "close": 0.2212,
      "volume": 89962.0
    },
    {
      "timestamp": 1762989240000,
      "open": 0.2211,
      "high": 0.2217,
      "low": 0.2207,
      "close": 0.221,
      "volume": 902258.0
    },
    {
      "timestamp": 1762989300000,
      "open": 0.221,
      "high": 0.221,
      "low": 0.2199,
      "close": 0.2204,
      "volume": 898321.0
    },
    {
      "timestamp": 1762989360000,
      "open": 0.2206,
      "high": 0.2209,
      "low": 0.2205,
      "close": 0.2205,
      "volume": 14914.0
    },
    {
      "timestamp": 1762989420000,
      "open": 0.2208,
      "high": 0.2208,
      "low": 0.2199,
      "close": 0.2199,
      "volume": 34152.0
    },
    {
      "timestamp": 1762989480000,
      "open": 0.22,
      "high": 0.2201,
      "low": 0.22,
      "close": 0.2201,
      "volume": 10892.0
    },
    {
      "timestamp": 1762989540000,
      "open": 0.2202,
      "high": 0.2204,
      "low": 0.2202,
      "close": 0.2203,
      "volume": 7471.0
    },
    {
      "timestamp": 1762989600000,
      "open": 0.2203,
      "high": 0.2203,
      "low": 0.2201,
      "close": 0.2201,
      "volume": 699.0
    },
    {
      "timestamp": 1762989660000,
      "open": 0.2204,
      "high": 0.2204,
      "low": 0.2204,
      "close": 0.2204,
      "volume": 103.0
    },
    {
      "timestamp": 1762989720000,
      "open": 0.2204,
      "high": 0.2204,
      "low": 0.2204,
      "close": 0.2204,
      "volume": 0.0
    },
    {
      "timestamp": 1762989780000,
      "open": 0.2204,
      "high": 0.2204,
      "low": 0.2204,
      "close": 0.2204,
      "volume": 0.0
    },
    {
      "timestamp": 1762989840000,
      "open": 0.2205,
      "high": 0.2205,
      "low": 0.2203,
      "close": 0.2203,
      "volume": 2388.0
    },
    {
      "timestamp": 1762989900000,
      "open": 0.2202,
      "high": 0.2203,
      "low": 0.2202,
      "close": 0.2202,
      "volume": 251.0
    },
    {
      "timestamp": 1762989960000,
      "open": 0.2203,
      "high": 0.2203,
      "low": 0.2202,
      "close": 0.2202,
      "volume": 3526.0
    },
    {
      "timestamp": 1762990020000,
      "open": 0.2202,
      "high": 0.2202,
      "low": 0.2202,
      "close": 0.2202,
      "volume": 0.0
    },
    {
      "timestamp": 1762990080000,
      "open": 0.2201,
      "high": 0.2201,
      "low": 0.2199,
      "close": 0.2199,
      "volume": 3720.0
    },
    {
      "timestamp": 1762990140000,
      "open": 0.2199,
      "high": 0.2199,
      "low": 0.2199,
      "close": 0.2199,
      "volume": 0.0
    },
    {
      "timestamp": 1762990200000,
      "open": 0.2199,
      "high": 0.2199,
      "low": 0.2198,
      "close": 0.2199,
      "volume": 4700.0
    },
    {
      "timestamp": 1762990260000,
      "open": 0.2197,
      "high": 0.2197,
      "low": 0.2196,
      "close": 0.2196,
      "volume": 570.0
    },
    {
      "timestamp": 1762990320000,
      "open": 0.2196,
      "high": 0.2196,
      "low": 0.2196,
      "close": 0.2196,
      "volume": 23.0
    },
    {
      "timestamp": 1762990380000,
      "open": 0.2196,
      "high": 0.2196,
      "low": 0.2196,
      "close": 0.2196,
      "volume": 0.0
    },
    {
      "timestamp": 1762990440000,
      "open": 0.2196,
      "high": 0.2196,
      "low": 0.2196,
      "close": 0.2196,
      "volume": 0.0
    },
    {
      "timestamp": 1762990500000,
      "open": 0.2199,
      "high": 0.2199,
      "low": 0.2199,
      "close": 0.2199,
      "volume": 28.0
    },
    {
      "timestamp": 1762990560000,
      "open": 0.2196,
      "high": 0.2197,
      "low": 0.2196,
      "close": 0.2197,
      "volume": 2935.0
    },
    {
      "timestamp": 1762990620000,
      "open": 0.2195,
      "high": 0.2195,
      "low": 0.2194,
      "close": 0.2194,
      "volume": 639.0
    },
    {
      "timestamp": 1762990680000,
      "open": 0.2194,
      "high": 0.2194,
      "low": 0.2194,
      "close": 0.2194,
      "volume": 0.0
    },
    {
      "timestamp": 1762990740000,
      "open": 0.2197,
      "high": 0.2197,
      "low": 0.2197,
      "close": 0.2197,
      "volume": 52.0
    },
    {
      "timestamp": 1762990800000,
      "open": 0.2197,
      "high": 0.2197,
      "low": 0.2197,
      "close": 0.2197,
      "volume": 0.0
    },
    {
      "timestamp": 1762990860000,
      "open": 0.2198,
      "high": 0.2198,
      "low": 0.2196,
      "close": 0.2196,
      "volume": 3354.0
    },
    {
      "timestamp": 1762990920000,
      "open": 0.2197,
      "high": 0.2197,
      "low": 0.2197,
      "close": 0.2197,
      "volume": 115.0
    },
    {
      "timestamp": 1762990980000,
      "open": 0.2197,
      "high": 0.2197,
      "low": 0.2197,
      "close": 0.2197,
      "volume": 0.0
    },
    {
      "timestamp": 1762991040000,
      "open": 0.2195,
      "high": 0.2198,
      "low": 0.2195,
      "close": 0.2196,
      "volume": 9837.0
    },
    {
      "timestamp": 1762991100000,
      "open": 0.2196,
      "high": 0.2196,
      "low": 0.2196,
      "close": 0.2196,
      "volume": 0.0
    },
    {
      "timestamp": 1762991160000,
      "open": 0.2196,
      "high": 0.2196,
      "low": 0.2192,
      "close": 0.2193,
      "volume": 8791.0
    },
    {
      "timestamp": 1762991220000,
      "open": 0.2191,
      "high": 0.2198,
      "low": 0.2191,
      "close": 0.2198,
      "volume": 1441.0
    },
    {
      "timestamp": 1762991280000,
      "open": 0.2199,
      "high": 0.2199,
      "low": 0.2199,
      "close": 0.2199,
      "volume": 31.0
    },
    {
      "timestamp": 1762991340000,
      "open": 0.2198,
      "high": 0.2198,
      "low": 0.2197,
      "close": 0.2197,
      "volume": 615.0
    },
    {
      "timestamp": 1762991400000,
      "open": 0.2197,
      "high": 0.2197,
      "low": 0.2197,
      "close": 0.2197,
      "volume": 0.0
    },
    {
      "timestamp": 1762991460000,
      "open": 0.2197,
      "high": 0.2197,
      "low": 0.2197,
      "close": 0.2197,
      "volume": 10916.0
    },
    {
      "timestamp": 1762991520000,
      "open": 0.2197,
      "high": 0.2197,
      "low": 0.2197,
      "close": 0.2197,
      "volume": 0.0
    },
    {
      "timestamp": 1762991580000,
      "open": 0.2197,
      "high": 0.2197,
      "low": 0.2197,
      "close": 0.2197,
      "volume": 113.0
    },
    {
      "timestamp": 1762991640000,
      "open": 0.2199,
      "high": 0.2199,
      "low": 0.2199,
      "close": 0.2199,
      "volume": 1232.0
    },
    {
      "timestamp": 1762991700000,
      "open": 0.22,
      "high": 0.22,
      "low": 0.22,
      "close": 0.22,
      "volume": 46.0
    },
    {
      "timestamp": 1762991760000,
      "open": 0.22,
      "high": 0.22,
      "low": 0.2198,
      "close": 0.2198,
      "volume": 3495.0
    },
    {
      "timestamp": 1762991820000,
      "open": 0.22,
      "high": 0.2202,
      "low": 0.22,
      "close": 0.2202,
      "volume": 509.0
    },
    {
      "timestamp": 1762991880000,
      "open": 0.2203,
      "high": 0.2203,
      "low": 0.2203,
      "close": 0.2203,
      "volume": 46.0
    },
    {
      "timestamp": 1762991940000,
      "open": 0.2203,
      "high": 0.2203,
      "low": 0.2202,
      "close": 0.2202,
      "volume": 462.0
    },
    {
      "timestamp": 1762992000000,
      "open": 0.2202,
      "high": 0.2204,
      "low": 0.2201,
      "close": 0.2202,
      "volume": 6323.0
    },
    {
      "timestamp": 1762992060000,
      "open": 0.2202,
      "high": 0.2202,
      "low": 0.22,
      "close": 0.22,
      "volume": 709.0
    },
    {
      "timestamp": 1762992120000,
      "open": 0.2201,
      "high": 0.2207,
      "low": 0.2201,
      "close": 0.2207,
      "volume": 4856.0
    },
    {
      "timestamp": 1762992180000,
      "open": 0.2208,
      "high": 0.2212,
      "low": 0.2208,
      "close": 0.2209,
      "volume": 4603.0
    },
    {
      "timestamp": 1762992240000,
      "open": 0.2209,
      "high": 0.221,
      "low": 0.2208,
      "close": 0.221,
      "volume": 14286.0
    },
    {
      "timestamp": 1762992300000,
      "open": 0.2211,
      "high": 0.2211,
      "low": 0.2211,
      "close": 0.2211,
      "volume": 605.0
    },
    {
      "timestamp": 1762992360000,
      "open": 0.221,
      "high": 0.221,
      "low": 0.2207,
      "close": 0.2207,
      "volume": 415.0
    },
    {
      "timestamp": 1762992420000,
      "open": 0.2209,
      "high": 0.2211,
      "low": 0.2209,
      "close": 0.2211,
      "volume": 159.0
    },
    {
      "timestamp": 1762992480000,
      "open": 0.2212,
      "high": 0.2212,
      "low": 0.221,
      "close": 0.2211,
      "volume": 220.0
    },
    {
      "timestamp": 1762992540000,
      "open": 0.2212,
      "high": 0.2212,
      "low": 0.2212,
      "close": 0.2212,
      "volume": 130.0
    },
    {
      "timestamp": 1762992600000,
      "open": 0.2213,
      "high": 0.2214,
      "low": 0.2211,
      "close": 0.2211,
      "volume": 1533.0
    },
    {
      "timestamp": 1762992660000,
      "open": 0.2211,
      "high": 0.2211,
      "low": 0.2211,
      "close": 0.2211,
      "volume": 318.0
    },
    {
      "timestamp": 1762992720000,
      "open": 0.221,
      "high": 0.221,
      "low": 0.221,
      "close": 0.221,
      "volume": 46.0
    },
    {
      "timestamp": 1762992780000,
      "open": 0.2209,
      "high": 0.2209,
      "low": 0.2206,
      "close": 0.2208,
      "volume": 1143.0
    },
    {
      "timestamp": 1762992840000,
      "open": 0.2209,
      "high": 0.2209,
      "low": 0.2209,
      "close": 0.2209,
      "volume": 101.0
    },
    {
      "timestamp": 1762992900000,
      "open": 0.221,
      "high": 0.2213,
      "low": 0.221,
      "close": 0.2213,
      "volume": 1453.0
    },
    {
      "timestamp": 1762992960000,
      "open": 0.2212,
      "high": 0.2212,
      "low": 0.2211,
      "close": 0.2211,
      "volume": 7024.0
    },
    {
      "timestamp": 1762993020000,
      "open": 0.2214,
      "high": 0.2214,
      "low": 0.2214,
      "close": 0.2214,
      "volume": 132.0
    },
    {
      "timestamp": 1762993080000,
      "open": 0.2215,
      "high": 0.2215,
      "low": 0.2213,
      "close": 0.2213,
      "volume": 638.0
    },
    {
      "timestamp": 1762993140000,
      "open": 0.2213,
      "high": 0.2213,
      "low": 0.2213,
      "close": 0.2213,
      "volume": 0.0
    },
    {
      "timestamp": 1762993200000,
      "open": 0.2212,
      "high": 0.2213,
      "low": 0.221,
      "close": 0.221,
      "volume": 348.0
    },
    {
      "timestamp": 1762993260000,
      "open": 0.2209,
      "high": 0.2209,
      "low": 0.2203,
      "close": 0.2203,
      "volume": 2175.0
    },
    {
      "timestamp": 1762993320000,
      "open": 0.2204,
      "high": 0.2205,
      "low": 0.2204,
      "close": 0.2205,
      "volume": 793.0
    },
    {
      "timestamp": 1762993380000,
      "open": 0.2204,
      "high": 0.2204,
      "low": 0.2202,
      "close": 0.2203,
      "volume": 738.0
    },
    {
      "timestamp": 1762993440000,
      "open": 0.2202,
      "high": 0.2202,
      "low": 0.2199,
      "close": 0.2199,
      "volume": 5567.0
    },
    {
      "timestamp": 1762993500000,
      "open": 0.2199,
      "high": 0.2199,
      "low": 0.2199,
      "close": 0.2199,
      "volume": 0.0
    },
    {
      "timestamp": 1762993560000,
      "open": 0.2199,
      "high": 0.22,
      "low": 0.2198,
      "close": 0.22,
      "volume": 10541.0
    },
    {
      "timestamp": 1762993620000,
      "open": 0.2201,
      "high": 0.2202,
      "low": 0.2201,
      "close": 0.2202,
      "volume": 1058.0
    },
    {
      "timestamp": 1762993680000,
      "open": 0.2201,
      "high": 0.2201,
      "low": 0.2201,
      "close": 0.2201,
      "volume": 46.0
    },
    {
      "timestamp": 1762993740000,
      "open": 0.2202,
      "high": 0.2202,
      "low": 0.2202,
      "close": 0.2202,
      "volume": 25.0
    },
    {
      "timestamp": 1762993800000,
      "open": 0.2202,
      "high": 0.2203,
      "low": 0.2202,
      "close": 0.2203,
      "volume": 830.0
    },
    {
      "timestamp": 1762993860000,
      "open": 0.2204,
      "high": 0.2207,
      "low": 0.2204,
      "close": 0.2207,
      "volume": 769.0
    },
    {
      "timestamp": 1762993920000,
      "open": 0.2207,
      "high": 0.2207,
      "low": 0.2207,
      "close": 0.2207,
      "volume": 91.0
    },
    {
      "timestamp": 1762993980000,
      "open": 0.2205,
      "high": 0.2206,
      "low": 0.2205,
      "close": 0.2205,
      "volume": 5769.0
    },
    {
      "timestamp": 1762994040000,
      "open": 0.2206,
      "high": 0.2207,
      "low": 0.2206,
      "close": 0.2206,
      "volume": 6353.0
    },
    {
      "timestamp": 1762994100000,
      "open": 0.2206,
      "high": 0.2216,
      "low": 0.2206,
      "close": 0.2216,
      "volume": 2416.0
    },
    {
      "timestamp": 1762994160000,
      "open": 0.2217,
      "high": 0.2223,
      "low": 0.2217,
      "close": 0.2218,
      "volume": 8699.0
    },
    {
      "timestamp": 1762994220000,
      "open": 0.2217,
      "high": 0.2219,
      "low": 0.2217,
      "close": 0.2218,
      "volume": 1891.0
    },
    {
      "timestamp": 1762994280000,
      "open": 0.2219,
      "high": 0.2221,
      "low": 0.2219,
      "close": 0.222,
      "volume": 2261.0
    },
    {
      "timestamp": 1762994340000,
      "open": 0.222,
      "high": 0.222,
      "low": 0.2217,
      "close": 0.2217,
      "volume": 37013.0
    },
    {
      "timestamp": 1762994400000,
      "open": 0.2218,
      "high": 0.2218,
      "low": 0.2215,
      "close": 0.2215,
      "volume": 40434.0
    },
    {
      "timestamp": 1762994460000,
      "open": 0.2214,
      "high": 0.2216,
      "low": 0.2214,
      "close": 0.2214,
      "volume": 1221.0
    },
    {
      "timestamp": 1762994520000,
      "open": 0.2213,
      "high": 0.2213,
      "low": 0.2211,
      "close": 0.2211,
      "volume": 1410.0
    },
    {
      "timestamp": 1762994580000,
      "open": 0.2211,
      "high": 0.2211,
      "low": 0.2207,
      "close": 0.2207,
      "volume": 6649.0
    },
    {
      "timestamp": 1762994640000,
      "open": 0.2208,
      "high": 0.221,
      "low": 0.2208,
      "close": 0.221,
      "volume": 3548.0
    },
    {
      "timestamp": 1762994700000,
      "open": 0.2211,
      "high": 0.2212,
      "low": 0.2211,
      "close": 0.2212,
      "volume": 2385.0
    },
    {
      "timestamp": 1762994760000,
      "open": 0.2211,
      "high": 0.2214,
      "low": 0.221,
      "close": 0.221,
      "volume": 3313.0
    },
    {
      "timestamp": 1762994820000,
      "open": 0.2209,
      "high": 0.2209,
      "low": 0.2208,
      "close": 0.2208,
      "volume": 565.0
    },
    {
      "timestamp": 1762994880000,
      "open": 0.2208,
      "high": 0.221,
      "low": 0.2208,
      "close": 0.2209,
      "volume": 664.0
    },
    {
      "timestamp": 1762994940000,
      "open": 0.221,
      "high": 0.221,
      "low": 0.2204,
      "close": 0.2204,
      "volume": 1149.0
    },
    {
      "timestamp": 1762995000000,
      "open": 0.2205,
      "high": 0.2206,
      "low": 0.2203,
      "close": 0.2206,
      "volume": 2344.0
    },
    {
      "timestamp": 1762995060000,
      "open": 0.2206,
      "high": 0.2206,
      "low": 0.2206,
      "close": 0.2206,
      "volume": 107.0
    },
    {
      "timestamp": 1762995120000,
      "open": 0.2205,
      "high": 0.2206,
      "low": 0.2205,
      "close": 0.2206,
      "volume": 3149.0
    },
    {
      "timestamp": 1762995180000,
      "open": 0.2206,
      "high": 0.2209,
      "low": 0.2206,
      "close": 0.2209,
      "volume": 1896.0
    },
    {
      "timestamp": 1762995240000,
      "open": 0.221,
      "high": 0.2211,
      "low": 0.221,
      "close": 0.2211,
      "volume": 145.0
    },
    {
      "timestamp": 1762995300000,
      "open": 0.2212,
      "high": 0.2213,
      "low": 0.2212,
      "close": 0.2212,
      "volume": 2818.0
    },
    {
      "timestamp": 1762995360000,
      "open": 0.2211,
      "high": 0.2211,
      "low": 0.2207,
      "close": 0.2208,
      "volume": 1517.0
    },
    {
      "timestamp": 1762995420000,
      "open": 0.2206,
      "high": 0.2206,
      "low": 0.2206,
      "close": 0.2206,
      "volume": 781.0
    },
    {
      "timestamp": 1762995480000,
      "open": 0.2205,
      "high": 0.2205,
      "low": 0.2205,
      "close": 0.2205,
      "volume": 111.0
    },
    {
      "timestamp": 1762995540000,
      "open": 0.2206,
      "high": 0.2207,
      "low": 0.2206,
      "close": 0.2207,
      "volume": 5204.0
    },
    {
      "timestamp": 1762995600000,
      "open": 0.2205,
      "high": 0.2205,
      "low": 0.2205,
      "close": 0.2205,
      "volume": 51.0
    },
    {
      "timestamp": 1762995660000,
      "open": 0.2207,
      "high": 0.2212,
      "low": 0.2207,
      "close": 0.2212,
      "volume": 4123.0
    },
    {
      "timestamp": 1762995720000,
      "open": 0.2213,
      "high": 0.2213,
      "low": 0.2213,
      "close": 0.2213,
      "volume": 5216.0
    },
    {
      "timestamp": 1762995780000,
      "open": 0.2214,
      "high": 0.2216,
      "low": 0.2214,
      "close": 0.2215,
      "volume": 27663.0
    },
    {
      "timestamp": 1762995840000,
      "open": 0.2214,
      "high": 0.2215,
      "low": 0.2212,
      "close": 0.2212,
      "volume": 14235.0
    },
    {
      "timestamp": 1762995900000,
      "open": 0.2213,
      "high": 0.2214,
      "low": 0.2213,
      "close": 0.2213,
      "volume": 2663.0
    },
    {
      "timestamp": 1762995960000,
      "open": 0.2214,
      "high": 0.2216,
      "low": 0.2214,
      "close": 0.2215,
      "volume": 1105.0
    },
    {
      "timestamp": 1762996020000,
      "open": 0.2216,
      "high": 0.2219,
      "low": 0.2216,
      "close": 0.2219,
      "volume": 2512.0
    },
    {
      "timestamp": 1762996080000,
      "open": 0.222,
      "high": 0.222,
      "low": 0.2217,
      "close": 0.2217,
      "volume": 988.0
    },
    {
      "timestamp": 1762996140000,
      "open": 0.2218,
      "high": 0.2222,
      "low": 0.2217,
      "close": 0.2222,
      "volume": 26506.0
    },
    {
      "timestamp": 1762996200000,
      "open": 0.2222,
      "high": 0.2229,
      "low": 0.222,
      "close": 0.2229,
      "volume": 11218.0
    },
    {
      "timestamp": 1762996260000,
      "open": 0.2228,
      "high": 0.2234,
      "low": 0.2226,
      "close": 0.2234,
      "volume": 64455.0
    },
    {
      "timestamp": 1762996320000,
      "open": 0.2235,
      "high": 0.224,
      "low": 0.2235,
      "close": 0.2235,
      "volume": 30886.0
    },
    {
      "timestamp": 1762996380000,
      "open": 0.2236,
      "high": 0.224,
      "low": 0.2235,
      "close": 0.2235,
      "volume": 3772.0
    },
    {
      "timestamp": 1762996440000,
      "open": 0.2236,
      "high": 0.2236,
      "low": 0.2234,
      "close": 0.2234,
      "volume": 11563.0
    },
    {
      "timestamp": 1762996500000,
      "open": 0.2234,
      "high": 0.2234,
      "low": 0.2225,
      "close": 0.2225,
      "volume": 49080.0
    },
    {
      "timestamp": 1762996560000,
      "open": 0.2224,
      "high": 0.2226,
      "low": 0.2223,
      "close": 0.2226,
      "volume": 11800.0
    },
    {
      "timestamp": 1762996620000,
      "open": 0.2227,
      "high": 0.2229,
      "low": 0.2227,
      "close": 0.2229,
      "volume": 2075.0
    },
    {
      "timestamp": 1762996680000,
      "open": 0.2229,
      "high": 0.2234,
      "low": 0.2229,
      "close": 0.2232,
      "volume": 59819.0
    },
    {
      "timestamp": 1762996740000,
      "open": 0.2232,
      "high": 0.2232,
      "low": 0.2227,
      "close": 0.2227,
      "volume": 23506.0
    },
    {
      "timestamp": 1762996800000,
      "open": 0.2226,
      "high": 0.2226,
      "low": 0.2221,
      "close": 0.2222,
      "volume": 6042.0
    },
    {
      "timestamp": 1762996860000,
      "open": 0.222,
      "high": 0.2222,
      "low": 0.2218,
      "close": 0.2222,
      "volume": 2187.0
    },
    {
      "timestamp": 1762996920000,
      "open": 0.2222,
      "high": 0.2222,
      "low": 0.2222,
      "close": 0.2222,
      "volume": 834.0
    },
    {
      "timestamp": 1762996980000,
      "open": 0.2221,
      "high": 0.2221,
      "low": 0.2221,
      "close": 0.2221,
      "volume": 92.0
    },
    {
      "timestamp": 1762997040000,
      "open": 0.222,
      "high": 0.222,
      "low": 0.2217,
      "close": 0.2217,
      "volume": 1950.0
    },
    {
      "timestamp": 1762997100000,
      "open": 0.2217,
      "high": 0.2218,
      "low": 0.2217,
      "close": 0.2217,
      "volume": 13756.0
    },
    {
      "timestamp": 1762997160000,
      "open": 0.2218,
      "high": 0.2218,
      "low": 0.2216,
      "close": 0.2218,
      "volume": 31096.0
    },
    {
      "timestamp": 1762997220000,
      "open": 0.2217,
      "high": 0.222,
      "low": 0.2217,
      "close": 0.2219,
      "volume": 32874.0
    },
    {
      "timestamp": 1762997280000,
      "open": 0.2219,
      "high": 0.2219,
      "low": 0.2214,
      "close": 0.2214,
      "volume": 510.0
    },
    {
      "timestamp": 1762997340000,
      "open": 0.2215,
      "high": 0.2222,
      "low": 0.2215,
      "close": 0.2222,
      "volume": 10795.0
    },
    {
      "timestamp": 1762997400000,
      "open": 0.2223,
      "high": 0.2224,
      "low": 0.222,
      "close": 0.2224,
      "volume": 13386.0
    },
    {
      "timestamp": 1762997460000,
      "open": 0.2225,
      "high": 0.2232,
      "low": 0.2225,
      "close": 0.2232,
      "volume": 2144.0
    },
    {
      "timestamp": 1762997520000,
      "open": 0.2229,
      "high": 0.2229,
      "low": 0.2225,
      "close": 0.2225,
      "volume": 2175.0
    },
    {
      "timestamp": 1762997580000,
      "open": 0.2224,
      "high": 0.2224,
      "low": 0.2223,
      "close": 0.2224,
      "volume": 2117.0
    },
    {
      "timestamp": 1762997640000,
      "open": 0.2225,
      "high": 0.2225,
      "low": 0.2225,
      "close": 0.2225,
      "volume": 46.0
    },
    {
      "timestamp": 1762997700000,
      "open": 0.2224,
      "high": 0.2224,
      "low": 0.2224,
      "close": 0.2224,
      "volume": 8473.0
    },
    {
      "timestamp": 1762997760000,
      "open": 0.2225,
      "high": 0.2225,
      "low": 0.2223,
      "close": 0.2223,
      "volume": 235.0
    },
    {
      "timestamp": 1762997820000,
      "open": 0.2225,
      "high": 0.2229,
      "low": 0.2225,
      "close": 0.2225,
      "volume": 34387.0
    },
    {
      "timestamp": 1762997880000,
      "open": 0.2227,
      "high": 0.2227,
      "low": 0.2227,
      "close": 0.2227,
      "volume": 46.0
    },
    {
      "timestamp": 1762997940000,
      "open": 0.2228,
      "high": 0.223,
      "low": 0.2228,
      "close": 0.223,
      "volume": 1492.0
    },
    {
      "timestamp": 1762998000000,
      "open": 0.2229,
      "high": 0.2229,
      "low": 0.2228,
      "close": 0.2228,
      "volume": 440.0
    },
    {
      "timestamp": 1762998060000,
      "open": 0.223,
      "high": 0.223,
      "low": 0.2228,
      "close": 0.2228,
      "volume": 138.0
    },
    {
      "timestamp": 1762998120000,
      "open": 0.2227,
      "high": 0.2231,
      "low": 0.2227,
      "close": 0.2231,
      "volume": 4797.0
    },
    {
      "timestamp": 1762998180000,
      "open": 0.2232,
      "high": 0.2232,
      "low": 0.2232,
      "close": 0.2232,
      "volume": 45.0
    },
    {
      "timestamp": 1762998240000,
      "open": 0.2232,
      "high": 0.2233,
      "low": 0.2232,
      "close": 0.2232,
      "volume": 1062.0
    },
    {
      "timestamp": 1762998300000,
      "open": 0.2231,
      "high": 0.2231,
      "low": 0.2229,
      "close": 0.2229,
      "volume": 2138.0
    },
    {
      "timestamp": 1762998360000,
      "open": 0.2229,
      "high": 0.2229,
      "low": 0.2229,
      "close": 0.2229,
      "volume": 3290.0
    },
    {
      "timestamp": 1762998420000,
      "open": 0.2229,
      "high": 0.2229,
      "low": 0.2227,
      "close": 0.2227,
      "volume": 3177.0
    },
    {
      "timestamp": 1762998480000,
      "open": 0.2227,
      "high": 0.2228,
      "low": 0.2223,
      "close": 0.2223,
      "volume": 11589.0
    },
    {
      "timestamp": 1762998540000,
      "open": 0.2222,
      "high": 0.2222,
      "low": 0.2222,
      "close": 0.2222,
      "volume": 46.0
    },
    {
      "timestamp": 1762998600000,
      "open": 0.2221,
      "high": 0.2221,
      "low": 0.2219,
      "close": 0.2219,
      "volume": 344.0
    },
    {
      "timestamp": 1762998660000,
      "open": 0.222,
      "high": 0.2221,
      "low": 0.222,
      "close": 0.2221,
      "volume": 942.0
    },
    {
      "timestamp": 1762998720000,
      "open": 0.2219,
      "high": 0.2221,
      "low": 0.2218,
      "close": 0.2221,
      "volume": 1062.0
    },
    {
      "timestamp": 1762998780000,
      "open": 0.2221,
      "high": 0.2221,
      "low": 0.2221,
      "close": 0.2221,
      "volume": 0.0
    },
    {
      "timestamp": 1762998840000,
      "open": 0.2222,
      "high": 0.2222,
      "low": 0.2222,
      "close": 0.2222,
      "volume": 84.0
    },
    {
      "timestamp": 1762998900000,
      "open": 0.2222,
      "high": 0.2222,
      "low": 0.2222,
      "close": 0.2222,
      "volume": 0.0
    },
    {
      "timestamp": 1762998960000,
      "open": 0.2221,
      "high": 0.2221,
      "low": 0.2219,
      "close": 0.2219,
      "volume": 4083.0
    },
    {
      "timestamp": 1762999020000,
      "open": 0.2218,
      "high": 0.2218,
      "low": 0.2216,
      "close": 0.2216,
      "volume": 95.0
    },
    {
      "timestamp": 1762999080000,
      "open": 0.2218,
      "high": 0.2218,
      "low": 0.2218,
      "close": 0.2218,
      "volume": 24.0
    },
    {
      "timestamp": 1762999140000,
      "open": 0.2217,
      "high": 0.2217,
      "low": 0.2217,
      "close": 0.2217,
      "volume": 1697.0
    },
    {
      "timestamp": 1762999200000,
      "open": 0.2216,
      "high": 0.2216,
      "low": 0.2215,
      "close": 0.2216,
      "volume": 1419.0
    },
    {
      "timestamp": 1762999260000,
      "open": 0.2216,
      "high": 0.222,
      "low": 0.2216,
      "close": 0.222,
      "volume": 5096.0
    },
    {
      "timestamp": 1762999320000,
      "open": 0.2219,
      "high": 0.2219,
      "low": 0.2219,
      "close": 0.2219,
      "volume": 84.0
    },
    {
      "timestamp": 1762999380000,
      "open": 0.2221,
      "high": 0.2222,
      "low": 0.2221,
      "close": 0.2222,
      "volume": 546.0
    },
    {
      "timestamp": 1762999440000,
      "open": 0.2222,
      "high": 0.2222,
      "low": 0.2222,
      "close": 0.2222,
      "volume": 0.0
    },
    {
      "timestamp": 1762999500000,
      "open": 0.2222,
      "high": 0.2222,
      "low": 0.2222,
      "close": 0.2222,
      "volume": 0.0
    },
    {
      "timestamp": 1762999560000,
      "open": 0.2223,
      "high": 0.2225,
      "low": 0.2223,
      "close": 0.2223,
      "volume": 1098.0
    },
    {
      "timestamp": 1762999620000,
      "open": 0.2222,
      "high": 0.2223,
      "low": 0.2222,
      "close": 0.2223,
      "volume": 127.0
    },
    {
      "timestamp": 1762999680000,
      "open": 0.2224,
      "high": 0.2225,
      "low": 0.2223,
      "close": 0.2223,
      "volume": 184.0
    },
    {
      "timestamp": 1762999740000,
      "open": 0.2223,
      "high": 0.2223,
      "low": 0.2221,
      "close": 0.2221,
      "volume": 1803.0
    },
    {
      "timestamp": 1762999800000,
      "open": 0.222,
      "high": 0.222,
      "low": 0.2217,
      "close": 0.2217,
      "volume": 4751.0
    },
    {
      "timestamp": 1762999860000,
      "open": 0.2218,
      "high": 0.2218,
      "low": 0.2217,
      "close": 0.2218,
      "volume": 138.0
    },
    {
      "timestamp": 1762999920000,
      "open": 0.2217,
      "high": 0.2217,
      "low": 0.2217,
      "close": 0.2217,
      "volume": 46.0
    },
    {
      "timestamp": 1762999980000,
      "open": 0.2218,
      "high": 0.2221,
      "low": 0.2218,
      "close": 0.2221,
      "volume": 1020.0
    },
    {
      "timestamp": 1763000040000,
      "open": 0.2221,
      "high": 0.2221,
      "low": 0.222,
      "close": 0.222,
      "volume": 872.0
    },
    {
      "timestamp": 1763000100000,
      "open": 0.222,
      "high": 0.222,
      "low": 0.222,
      "close": 0.222,
      "volume": 0.0
    },
    {
      "timestamp": 1763000160000,
      "open": 0.2221,
      "high": 0.2221,
      "low": 0.2219,
      "close": 0.2219,
      "volume": 6073.0
    },
    {
      "timestamp": 1763000220000,
      "open": 0.2222,
      "high": 0.2222,
      "low": 0.2222,
      "close": 0.2222,
      "volume": 878.0
    },
    {
      "timestamp": 1763000280000,
      "open": 0.2223,
      "high": 0.2223,
      "low": 0.2223,
      "close": 0.2223,
      "volume": 305.0
    },
    {
      "timestamp": 1763000340000,
      "open": 0.2222,
      "high": 0.2224,
      "low": 0.2222,
      "close": 0.2224,
      "volume": 1194.0
    },
    {
      "timestamp": 1763000400000,
      "open": 0.2224,
      "high": 0.2224,
      "low": 0.2222,
      "close": 0.2223,
      "volume": 1218.0
    },
    {
      "timestamp": 1763000460000,
      "open": 0.2224,
      "high": 0.2225,
      "low": 0.2224,
      "close": 0.2225,
      "volume": 3795.0
    },
    {
      "timestamp": 1763000520000,
      "open": 0.2224,
      "high": 0.2224,
      "low": 0.222,
      "close": 0.222,
      "volume": 5573.0
    },
    {
      "timestamp": 1763000580000,
      "open": 0.2219,
      "high": 0.222,
      "low": 0.2219,
      "close": 0.222,
      "volume": 144.0
    },
    {
      "timestamp": 1763000640000,
      "open": 0.222,
      "high": 0.222,
      "low": 0.2219,
      "close": 0.2219,
      "volume": 5380.0
    },
    {
      "timestamp": 1763000700000,
      "open": 0.2218,
      "high": 0.2218,
      "low": 0.2218,
      "close": 0.2218,
      "volume": 46.0
    },
    {
      "timestamp": 1763000760000,
      "open": 0.2219,
      "high": 0.2221,
      "low": 0.2219,
      "close": 0.2221,
      "volume": 2349.0
    },
    {
      "timestamp": 1763000820000,
      "open": 0.222,
      "high": 0.222,
      "low": 0.2217,
      "close": 0.2217,
      "volume": 2571.0
    },
    {
      "timestamp": 1763000880000,
      "open": 0.2216,
      "high": 0.2216,
      "low": 0.2216,
      "close": 0.2216,
      "volume": 204.0
    },
    {
      "timestamp": 1763000940000,
      "open": 0.2215,
      "high": 0.2215,
      "low": 0.2211,
      "close": 0.2212,
      "volume": 7062.0
    },
    {
      "timestamp": 1763001000000,
      "open": 0.2211,
      "high": 0.2212,
      "low": 0.2209,
      "close": 0.2212,
      "volume": 2999.0
    },
    {
      "timestamp": 1763001060000,
      "open": 0.2213,
      "high": 0.2213,
      "low": 0.2213,
      "close": 0.2213,
      "volume": 159.0
    },
    {
      "timestamp": 1763001120000,
      "open": 0.2214,
      "high": 0.2218,
      "low": 0.2214,
      "close": 0.2218,
      "volume": 2329.0
    },
    {
      "timestamp": 1763001180000,
      "open": 0.2219,
      "high": 0.2223,
      "low": 0.2219,
      "close": 0.2223,
      "volume": 1823.0
    },
    {
      "timestamp": 1763001240000,
      "open": 0.2224,
      "high": 0.2224,
      "low": 0.2224,
      "close": 0.2224,
      "volume": 804.0
    },
    {
      "timestamp": 1763001300000,
      "open": 0.2225,
      "high": 0.2228,
      "low": 0.2225,
      "close": 0.2228,
      "volume": 7903.0
    },
    {
      "timestamp": 1763001360000,
      "open": 0.2228,
      "high": 0.2228,
      "low": 0.2228,
      "close": 0.2228,
      "volume": 760.0
    },
    {
      "timestamp": 1763001420000,
      "open": 0.2229,
      "high": 0.2229,
      "low": 0.2228,
      "close": 0.2228,
      "volume": 4353.0
    },
    {
      "timestamp": 1763001480000,
      "open": 0.2227,
      "high": 0.2227,
      "low": 0.2222,
      "close": 0.2222,
      "volume": 2915.0
    },
    {
      "timestamp": 1763001540000,
      "open": 0.2223,
      "high": 0.2224,
      "low": 0.2223,
      "close": 0.2224,
      "volume": 144.0
    },
    {
      "timestamp": 1763001600000,
      "open": 0.2222,
      "high": 0.2222,
      "low": 0.2222,
      "close": 0.2222,
      "volume": 46.0
    },
    {
      "timestamp": 1763001660000,
      "open": 0.2222,
      "high": 0.2224,
      "low": 0.2222,
      "close": 0.2223,
      "volume": 2628.0
    },
    {
      "timestamp": 1763001720000,
      "open": 0.2222,
      "high": 0.2224,
      "low": 0.2222,
      "close": 0.2224,
      "volume": 2370.0
    },
    {
      "timestamp": 1763001780000,
      "open": 0.2222,
      "high": 0.2222,
      "low": 0.2222,
      "close": 0.2222,
      "volume": 1140.0
    },
    {
      "timestamp": 1763001840000,
      "open": 0.2221,
      "high": 0.2221,
      "low": 0.2221,
      "close": 0.2221,
      "volume": 46.0
    },
    {
      "timestamp": 1763001900000,
      "open": 0.222,
      "high": 0.2221,
      "low": 0.2219,
      "close": 0.2219,
      "volume": 2368.0
    },
    {
      "timestamp": 1763001960000,
      "open": 0.2218,
      "high": 0.2218,
      "low": 0.2216,
      "close": 0.2216,
      "volume": 4503.0
    },
    {
      "timestamp": 1763002020000,
      "open": 0.2216,
      "high": 0.222,
      "low": 0.2216,
      "close": 0.222,
      "volume": 1829.0
    },
    {
      "timestamp": 1763002080000,
      "open": 0.2221,
      "high": 0.2222,
      "low": 0.2221,
      "close": 0.2222,
      "volume": 1540.0
    },
    {
      "timestamp": 1763002140000,
      "open": 0.2221,
      "high": 0.2223,
      "low": 0.2221,
      "close": 0.2223,
      "volume": 5005.0
    },
    {
      "timestamp": 1763002200000,
      "open": 0.2222,
      "high": 0.2222,
      "low": 0.2222,
      "close": 0.2222,
      "volume": 792.0
    },
    {
      "timestamp": 1763002260000,
      "open": 0.2221,
      "high": 0.2221,
      "low": 0.2221,
      "close": 0.2221,
      "volume": 46.0
    },
    {
      "timestamp": 1763002320000,
      "open": 0.222,
      "high": 0.222,
      "low": 0.2216,
      "close": 0.2216,
      "volume": 1211.0
    },
    {
      "timestamp": 1763002380000,
      "open": 0.2217,
      "high": 0.2217,
      "low": 0.2215,
      "close": 0.2215,
      "volume": 6243.0
    },
    {
      "timestamp": 1763002440000,
      "open": 0.2216,
      "high": 0.2217,
      "low": 0.2216,
      "close": 0.2217,
      "volume": 15503.0
    },
    {
      "timestamp": 1763002500000,
      "open": 0.2217,
      "high": 0.2218,
      "low": 0.2216,
      "close": 0.2216,
      "volume": 4214.0
    },
    {
      "timestamp": 1763002560000,
      "open": 0.2216,
      "high": 0.2216,
      "low": 0.2216,
      "close": 0.2216,
      "volume": 797.0
    },
    {
      "timestamp": 1763002620000,
      "open": 0.2216,
      "high": 0.2216,
      "low": 0.2216,
      "close": 0.2216,
      "volume": 46.0
    },
    {
      "timestamp": 1763002680000,
      "open": 0.2216,
      "high": 0.2216,
      "low": 0.2216,
      "close": 0.2216,
      "volume": 0.0
    },
    {
      "timestamp": 1763002740000,
      "open": 0.2217,
      "high": 0.2218,
      "low": 0.2217,
      "close": 0.2218,
      "volume": 92.0
    },
    {
      "timestamp": 1763002800000,
      "open": 0.2218,
      "high": 0.2219,
      "low": 0.2217,
      "close": 0.2219,
      "volume": 4558.0
    },
    {
      "timestamp": 1763002860000,
      "open": 0.2218,
      "high": 0.2218,
      "low": 0.2217,
      "close": 0.2217,
      "volume": 8917.0
    },
    {
      "timestamp": 1763002920000,
      "open": 0.2217,
      "high": 0.2217,
      "low": 0.2214,
      "close": 0.2214,
      "volume": 7490.0
    },
    {
      "timestamp": 1763002980000,
      "open": 0.2213,
      "high": 0.2213,
      "low": 0.2212,
      "close": 0.2212,
      "volume": 2674.0
    },
    {
      "timestamp": 1763003040000,
      "open": 0.2214,
      "high": 0.2214,
      "low": 0.2213,
      "close": 0.2213,
      "volume": 92.0
    },
    {
      "timestamp": 1763003100000,
      "open": 0.2213,
      "high": 0.2215,
      "low": 0.2213,
      "close": 0.2213,
      "volume": 9525.0
    },
    {
      "timestamp": 1763003160000,
      "open": 0.2214,
      "high": 0.2215,
      "low": 0.2214,
      "close": 0.2215,
      "volume": 810.0
    },
    {
      "timestamp": 1763003220000,
      "open": 0.2215,
      "high": 0.2215,
      "low": 0.2213,
      "close": 0.2213,
      "volume": 11310.0
    },
    {
      "timestamp": 1763003280000,
      "open": 0.2212,
      "high": 0.2212,
      "low": 0.2211,
      "close": 0.2211,
      "volume": 1236.0
    },
    {
      "timestamp": 1763003340000,
      "open": 0.221,
      "high": 0.221,
      "low": 0.2207,
      "close": 0.2207,
      "volume": 40363.0
    },
    {
      "timestamp": 1763003400000,
      "open": 0.2207,
      "high": 0.2207,
      "low": 0.2198,
      "close": 0.2198,
      "volume": 19976.0
    },
    {
      "timestamp": 1763003460000,
      "open": 0.2199,
      "high": 0.2203,
      "low": 0.2199,
      "close": 0.2203,
      "volume": 32589.0
    },
    {
      "timestamp": 1763003520000,
      "open": 0.2201,
      "high": 0.2202,
      "low": 0.2201,
      "close": 0.2202,
      "volume": 92.0
    },
    {
      "timestamp": 1763003580000,
      "open": 0.2201,
      "high": 0.2201,
      "low": 0.2197,
      "close": 0.2198,
      "volume": 745.0
    },
    {
      "timestamp": 1763003640000,
      "open": 0.2196,
      "high": 0.2197,
      "low": 0.219,
      "close": 0.2193,
      "volume": 16744.0
    },
    {
      "timestamp": 1763003700000,
      "open": 0.2192,
      "high": 0.2193,
      "low": 0.2178,
      "close": 0.2181,
      "volume": 97293.0
    },
    {
      "timestamp": 1763003760000,
      "open": 0.2179,
      "high": 0.2199,
      "low": 0.2178,
      "close": 0.2199,
      "volume": 71434.0
    },
    {
      "timestamp": 1763003820000,
      "open": 0.2199,
      "high": 0.2212,
      "low": 0.2197,
      "close": 0.2207,
      "volume": 18508.0
    },
    {
      "timestamp": 1763003880000,
      "open": 0.2207,
      "high": 0.2211,
      "low": 0.2207,
      "close": 0.221,
      "volume": 396.0
    },
    {
      "timestamp": 1763003940000,
      "open": 0.2211,
      "high": 0.2211,
      "low": 0.2208,
      "close": 0.221,
      "volume": 1529.0
    },
    {
      "timestamp": 1763004000000,
      "open": 0.2211,
      "high": 0.2211,
      "low": 0.2209,
      "close": 0.221,
      "volume": 278.0
    },
    {
      "timestamp": 1763004060000,
      "open": 0.2209,
      "high": 0.2209,
      "low": 0.2208,
      "close": 0.2209,
      "volume": 812.0
    },
    {
      "timestamp": 1763004120000,
      "open": 0.2208,
      "high": 0.221,
      "low": 0.2208,
      "close": 0.221,
      "volume": 469.0
    },
    {
      "timestamp": 1763004180000,
      "open": 0.2211,
      "high": 0.2211,
      "low": 0.221,
      "close": 0.221,
      "volume": 12982.0
    },
    {
      "timestamp": 1763004240000,
      "open": 0.2212,
      "high": 0.2215,
      "low": 0.2212,
      "close": 0.2214,
      "volume": 19844.0
    },
    {
      "timestamp": 1763004300000,
      "open": 0.2214,
      "high": 0.2225,
      "low": 0.2214,
      "close": 0.2225,
      "volume": 12677.0
    },
    {
      "timestamp": 1763004360000,
      "open": 0.2226,
      "high": 0.2226,
      "low": 0.2224,
      "close": 0.2224,
      "volume": 993.0
    },
    {
      "timestamp": 1763004420000,
      "open": 0.2223,
      "high": 0.2223,
      "low": 0.2221,
      "close": 0.2222,
      "volume": 1628.0
    },
    {
      "timestamp": 1763004480000,
      "open": 0.2223,
      "high": 0.2229,
      "low": 0.2223,
      "close": 0.2228,
      "volume": 6202.0
    },
    {
      "timestamp": 1763004540000,
      "open": 0.2227,
      "high": 0.2227,
      "low": 0.2227,
      "close": 0.2227,
      "volume": 46.0
    },
    {
      "timestamp": 1763004600000,
      "open": 0.223,
      "high": 0.2242,
      "low": 0.223,
      "close": 0.2241,
      "volume": 11275.0
    },
    {
      "timestamp": 1763004660000,
      "open": 0.2241,
      "high": 0.2243,
      "low": 0.2234,
      "close": 0.2234,
      "volume": 26931.0
    },
    {
      "timestamp": 1763004720000,
      "open": 0.2235,
      "high": 0.2238,
      "low": 0.2235,
      "close": 0.2238,
      "volume": 2975.0
    },
    {
      "timestamp": 1763004780000,
      "open": 0.2238,
      "high": 0.2242,
      "low": 0.2235,
      "close": 0.2236,
      "volume": 3741.0
    },
    {
      "timestamp": 1763004840000,
      "open": 0.2238,
      "high": 0.2238,
      "low": 0.2232,
      "close": 0.2233,
      "volume": 1911.0
    },
    {
      "timestamp": 1763004900000,
      "open": 0.2235,
      "high": 0.2237,
      "low": 0.2235,
      "close": 0.2237,
      "volume": 683.0
    },
    {
      "timestamp": 1763004960000,
      "open": 0.2236,
      "high": 0.2236,
      "low": 0.2234,
      "close": 0.2235,
      "volume": 729.0
    },
    {
      "timestamp": 1763005020000,
      "open": 0.2237,
      "high": 0.2241,
      "low": 0.2237,
      "close": 0.2241,
      "volume": 750.0
    },
    {
      "timestamp": 1763005080000,
      "open": 0.2242,
      "high": 0.2242,
      "low": 0.2241,
      "close": 0.2241,
      "volume": 270.0
    },
    {
      "timestamp": 1763005140000,
      "open": 0.224,
      "high": 0.2248,
      "low": 0.224,
      "close": 0.2245,
      "volume": 5846.0
    },
    {
      "timestamp": 1763005200000,
      "open": 0.2247,
      "high": 0.2248,
      "low": 0.2245,
      "close": 0.2247,
      "volume": 378.0
    },
    {
      "timestamp": 1763005260000,
      "open": 0.2247,
      "high": 0.2251,
      "low": 0.2247,
      "close": 0.2251,
      "volume": 32439.0
    },
    {
      "timestamp": 1763005320000,
      "open": 0.2251,
      "high": 0.2255,
      "low": 0.225,
      "close": 0.2251,
      "volume": 7569.0
    },
    {
      "timestamp": 1763005380000,
      "open": 0.2252,
      "high": 0.2256,
      "low": 0.2252,
      "close": 0.2252,
      "volume": 3571.0
    },
    {
      "timestamp": 1763005440000,
      "open": 0.2255,
      "high": 0.2255,
      "low": 0.2247,
      "close": 0.2247,
      "volume": 2371.0
    },
    {
      "timestamp": 1763005500000,
      "open": 0.2248,
      "high": 0.2249,
      "low": 0.2247,
      "close": 0.2249,
      "volume": 1617.0
    },
    {
      "timestamp": 1763005560000,
      "open": 0.2249,
      "high": 0.2251,
      "low": 0.2249,
      "close": 0.2249,
      "volume": 2941.0
    },
    {
      "timestamp": 1763005620000,
      "open": 0.2248,
      "high": 0.225,
      "low": 0.2245,
      "close": 0.225,
      "volume": 5800.0
    },
    {
      "timestamp": 1763005680000,
      "open": 0.225,
      "high": 0.2258,
      "low": 0.225,
      "close": 0.2258,
      "volume": 27446.0
    },
    {
      "timestamp": 1763005740000,
      "open": 0.2258,
      "high": 0.226,
      "low": 0.2257,
      "close": 0.226,
      "volume": 33094.0
    },
    {
      "timestamp": 1763005800000,
      "open": 0.226,
      "high": 0.2263,
      "low": 0.2255,
      "close": 0.2255,
      "volume": 7754.0
    },
    {
      "timestamp": 1763005860000,
      "open": 0.2257,
      "high": 0.2257,
      "low": 0.2253,
      "close": 0.2253,
      "volume": 1081.0
    },
    {
      "timestamp": 1763005920000,
      "open": 0.2252,
      "high": 0.2252,
      "low": 0.2249,
      "close": 0.2249,
      "volume": 10455.0
    },
    {
      "timestamp": 1763005980000,
      "open": 0.2251,
      "high": 0.2251,
      "low": 0.2248,
      "close": 0.2248,
      "volume": 803.0
    },
    {
      "timestamp": 1763006040000,
      "open": 0.225,
      "high": 0.2251,
      "low": 0.2249,
      "close": 0.2249,
      "volume": 1349.0
    },
    {
      "timestamp": 1763006100000,
      "open": 0.225,
      "high": 0.225,
      "low": 0.2247,
      "close": 0.2247,
      "volume": 9688.0
    },
    {
      "timestamp": 1763006160000,
      "open": 0.2247,
      "high": 0.2247,
      "low": 0.2246,
      "close": 0.2247,
      "volume": 359.0
    },
    {
      "timestamp": 1763006220000,
      "open": 0.2246,
      "high": 0.2248,
      "low": 0.2246,
      "close": 0.2248,
      "volume": 6802.0
    },
    {
      "timestamp": 1763006280000,
      "open": 0.2247,
      "high": 0.2247,
      "low": 0.2246,
      "close": 0.2246,
      "volume": 2190.0
    },
    {
      "timestamp": 1763006340000,
      "open": 0.2245,
      "high": 0.2245,
      "low": 0.2242,
      "close": 0.2242,
      "volume": 2520.0
    },
    {
      "timestamp": 1763006400000,
      "open": 0.2242,
      "high": 0.2242,
      "low": 0.2242,
      "close": 0.2242,
      "volume": 1183.0
    },
    {
      "timestamp": 1763006460000,
      "open": 0.2241,
      "high": 0.2241,
      "low": 0.2235,
      "close": 0.2237,
      "volume": 2522.0
    },
    {
      "timestamp": 1763006520000,
      "open": 0.2236,
      "high": 0.2236,
      "low": 0.2234,
      "close": 0.2234,
      "volume": 303.0
    },
    {
      "timestamp": 1763006580000,
      "open": 0.2233,
      "high": 0.2233,
      "low": 0.223,
      "close": 0.2232,
      "volume": 4380.0
    },
    {
      "timestamp": 1763006640000,
      "open": 0.2231,
      "high": 0.2234,
      "low": 0.223,
      "close": 0.2232,
      "volume": 2875.0
    },
    {
      "timestamp": 1763006700000,
      "open": 0.2231,
      "high": 0.2231,
      "low": 0.2226,
      "close": 0.2226,
      "volume": 1564.0
    },
    {
      "timestamp": 1763006760000,
      "open": 0.2227,
      "high": 0.2229,
      "low": 0.2225,
      "close": 0.2225,
      "volume": 2510.0
    },
    {
      "timestamp": 1763006820000,
      "open": 0.2226,
      "high": 0.2226,
      "low": 0.2223,
      "close": 0.2226,
      "volume": 2269.0
    },
    {
      "timestamp": 1763006880000,
      "open": 0.2227,
      "high": 0.2231,
      "low": 0.2227,
      "close": 0.2229,
      "volume": 5073.0
    },
    {
      "timestamp": 1763006940000,
      "open": 0.2229,
      "high": 0.223,
      "low": 0.2227,
      "close": 0.223,
      "volume": 15130.0
    },
    {
      "timestamp": 1763007000000,
      "open": 0.223,
      "high": 0.223,
      "low": 0.2229,
      "close": 0.2229,
      "volume": 7272.0
    },
    {
      "timestamp": 1763007060000,
      "open": 0.223,
      "high": 0.2231,
      "low": 0.2229,
      "close": 0.223,
      "volume": 1303.0
    },
    {
      "timestamp": 1763007120000,
      "open": 0.2231,
      "high": 0.2231,
      "low": 0.2229,
      "close": 0.223,
      "volume": 1127.0
    },
    {
      "timestamp": 1763007180000,
      "open": 0.223,
      "high": 0.2239,
      "low": 0.223,
      "close": 0.2239,
      "volume": 71777.0
    },
    {
      "timestamp": 1763007240000,
      "open": 0.2238,
      "high": 0.2245,
      "low": 0.2238,
      "close": 0.2245,
      "volume": 23798.0
    },
    {
      "timestamp": 1763007300000,
      "open": 0.2246,
      "high": 0.2248,
      "low": 0.2242,
      "close": 0.2242,
      "volume": 7156.0
    },
    {
      "timestamp": 1763007360000,
      "open": 0.2242,
      "high": 0.2242,
      "low": 0.2233,
      "close": 0.2233,
      "volume": 8205.0
    },
    {
      "timestamp": 1763007420000,
      "open": 0.2233,
      "high": 0.2251,
      "low": 0.2233,
      "close": 0.225,
      "volume": 69121.0
    },
    {
      "timestamp": 1763007480000,
      "open": 0.225,
      "high": 0.225,
      "low": 0.2247,
      "close": 0.2247,
      "volume": 6127.0
    },
    {
      "timestamp": 1763007540000,
      "open": 0.2247,
      "high": 0.225,
      "low": 0.2247,
      "close": 0.2249,
      "volume": 1377.0
    },
    {
      "timestamp": 1763007600000,
      "open": 0.2248,
      "high": 0.2248,
      "low": 0.2247,
      "close": 0.2248,
      "volume": 1502.0
    },
    {
      "timestamp": 1763007660000,
      "open": 0.2248,
      "high": 0.2252,
      "low": 0.2248,
      "close": 0.2251,
      "volume": 699.0
    },
    {
      "timestamp": 1763007720000,
      "open": 0.225,
      "high": 0.2251,
      "low": 0.2248,
      "close": 0.2251,
      "volume": 360.0
    },
    {
      "timestamp": 1763007780000,
      "open": 0.2251,
      "high": 0.2251,
      "low": 0.2251,
      "close": 0.2251,
      "volume": 656.0
    },
    {
      "timestamp": 1763007840000,
      "open": 0.2252,
      "high": 0.2253,
      "low": 0.2252,
      "close": 0.2252,
      "volume": 354.0
    },
    {
      "timestamp": 1763007900000,
      "open": 0.2253,
      "high": 0.2253,
      "low": 0.2252,
      "close": 0.2253,
      "volume": 3053.0
    },
    {
      "timestamp": 1763007960000,
      "open": 0.2252,
      "high": 0.2254,
      "low": 0.2252,
      "close": 0.2252,
      "volume": 2993.0
    },
    {
      "timestamp": 1763008020000,
      "open": 0.2252,
      "high": 0.2253,
      "low": 0.2251,
      "close": 0.2251,
      "volume": 862.0
    },
    {
      "timestamp": 1763008080000,
      "open": 0.225,
      "high": 0.225,
      "low": 0.2249,
      "close": 0.2249,
      "volume": 618.0
    },
    {
      "timestamp": 1763008140000,
      "open": 0.2248,
      "high": 0.2248,
      "low": 0.2247,
      "close": 0.2247,
      "volume": 2170.0
    },
    {
      "timestamp": 1763008200000,
      "open": 0.2246,
      "high": 0.2246,
      "low": 0.2243,
      "close": 0.2243,
      "volume": 776.0
    },
    {
      "timestamp": 1763008260000,
      "open": 0.2243,
      "high": 0.2244,
      "low": 0.2241,
      "close": 0.2243,
      "volume": 1975.0
    },
    {
      "timestamp": 1763008320000,
      "open": 0.2244,
      "high": 0.2247,
      "low": 0.2244,
      "close": 0.2245,
      "volume": 17525.0
    },
    {
      "timestamp": 1763008380000,
      "open": 0.2247,
      "high": 0.2247,
      "low": 0.2245,
      "close": 0.2245,
      "volume": 1966.0
    },
    {
      "timestamp": 1763008440000,
      "open": 0.2244,
      "high": 0.2244,
      "low": 0.2236,
      "close": 0.2236,
      "volume": 17692.0
    },
    {
      "timestamp": 1763008500000,
      "open": 0.2236,
      "high": 0.2237,
      "low": 0.2234,
      "close": 0.2234,
      "volume": 619.0
    },
    {
      "timestamp": 1763008560000,
      "open": 0.2234,
      "high": 0.2234,
      "low": 0.2234,
      "close": 0.2234,
      "volume": 0.0
    },
    {
      "timestamp": 1763008620000,
      "open": 0.2237,
      "high": 0.2237,
      "low": 0.2236,
      "close": 0.2236,
      "volume": 113.0
    },
    {
      "timestamp": 1763008680000,
      "open": 0.2236,
      "high": 0.2236,
      "low": 0.2236,
      "close": 0.2236,
      "volume": 39.0
    },
    {
      "timestamp": 1763008740000,
      "open": 0.2236,
      "high": 0.2237,
      "low": 0.2236,
      "close": 0.2237,
      "volume": 1523.0
    },
    {
      "timestamp": 1763008800000,
      "open": 0.2238,
      "high": 0.2239,
      "low": 0.2237,
      "close": 0.2237,
      "volume": 11765.0
    },
    {
      "timestamp": 1763008860000,
      "open": 0.2236,
      "high": 0.2241,
      "low": 0.2236,
      "close": 0.2241,
      "volume": 102034.0
    },
    {
      "timestamp": 1763008920000,
      "open": 0.224,
      "high": 0.2243,
      "low": 0.224,
      "close": 0.2241,
      "volume": 34877.0
    },
    {
      "timestamp": 1763008980000,
      "open": 0.224,
      "high": 0.224,
      "low": 0.2238,
      "close": 0.2238,
      "volume": 937.0
    },
    {
      "timestamp": 1763009040000,
      "open": 0.2237,
      "high": 0.2238,
      "low": 0.2237,
      "close": 0.2237,
      "volume": 10426.0
    },
    {
      "timestamp": 1763009100000,
      "open": 0.2237,
      "high": 0.2237,
      "low": 0.2236,
      "close": 0.2237,
      "volume": 4550.0
    },
    {
      "timestamp": 1763009160000,
      "open": 0.2236,
      "high": 0.2236,
      "low": 0.2235,
      "close": 0.2235,
      "volume": 148.0
    },
    {
      "timestamp": 1763009220000,
      "open": 0.2235,
      "high": 0.2235,
      "low": 0.2231,
      "close": 0.2231,
      "volume": 56588.0
    },
    {
      "timestamp": 1763009280000,
      "open": 0.2232,
      "high": 0.2236,
      "low": 0.2232,
      "close": 0.2236,
      "volume": 4125.0
    },
    {
      "timestamp": 1763009340000,
      "open": 0.2236,
      "high": 0.2236,
      "low": 0.2232,
      "close": 0.2232,
      "volume": 9693.0
    },
    {
      "timestamp": 1763009400000,
      "open": 0.2231,
      "high": 0.2231,
      "low": 0.2228,
      "close": 0.2228,
      "volume": 28794.0
    },
    {
      "timestamp": 1763009460000,
      "open": 0.2227,
      "high": 0.2227,
      "low": 0.2227,
      "close": 0.2227,
      "volume": 1179.0
    },
    {
      "timestamp": 1763009520000,
      "open": 0.2226,
      "high": 0.2234,
      "low": 0.2226,
      "close": 0.2234,
      "volume": 26480.0
    },
    {
      "timestamp": 1763009580000,
      "open": 0.2233,
      "high": 0.2233,
      "low": 0.2232,
      "close": 0.2232,
      "volume": 9005.0
    },
    {
      "timestamp": 1763009640000,
      "open": 0.2232,
      "high": 0.2232,
      "low": 0.2232,
      "close": 0.2232,
      "volume": 0.0
    },
    {
      "timestamp": 1763009700000,
      "open": 0.2235,
      "high": 0.2236,
      "low": 0.2232,
      "close": 0.2233,
      "volume": 10614.0
    },
    {
      "timestamp": 1763009760000,
      "open": 0.2231,
      "high": 0.2233,
      "low": 0.223,
      "close": 0.2231,
      "volume": 189771.0
    },
    {
      "timestamp": 1763009820000,
      "open": 0.2232,
      "high": 0.2244,
      "low": 0.2232,
      "close": 0.2244,
      "volume": 26313.0
    },
    {
      "timestamp": 1763009880000,
      "open": 0.2242,
      "high": 0.2242,
      "low": 0.2238,
      "close": 0.2238,
      "volume": 8122.0
    },
    {
      "timestamp": 1763009940000,
      "open": 0.2238,
      "high": 0.2238,
      "low": 0.2238,
      "close": 0.2238,
      "volume": 0.0
    },
    {
      "timestamp": 1763010000000,
      "open": 0.2237,
      "high": 0.2237,
      "low": 0.2235,
      "close": 0.2235,
      "volume": 2884.0
    },
    {
      "timestamp": 1763010060000,
      "open": 0.2235,
      "high": 0.2235,
      "low": 0.2235,
      "close": 0.2235,
      "volume": 0.0
    }
  ]
}